{"comment": [{"rating": "1", "vote_num": "1010", "author": {"link": "https://www.douban.com/people/shihaolou/", "name": "\u788e\u5c81"}}, {"rating": "5", "vote_num": "638", "author": {"link": "https://www.douban.com/people/HardCandy/", "name": "\u5f20\u5929\u5e08"}}, {"rating": "1", "vote_num": "556", "author": {"link": "https://www.douban.com/people/fiammanda/", "name": "\u8fd9\u4e2a\u59d1\u5a18\u592a\u626f\u4e86"}}, {"rating": "2", "vote_num": "507", "author": {"link": "https://www.douban.com/people/1751103/", "name": "Eclipse"}}, {"rating": "2", "vote_num": "393", "author": {"link": "https://www.douban.com/people/laoafei/", "name": "\u8001\u963f\u98de\u2014\u6545\u56ed"}}, {"rating": "4", "vote_num": "502", "author": {"link": "https://www.douban.com/people/babyblue/", "name": "\u9732\u5a1cpeace"}}, {"rating": "2", "vote_num": "375", "author": {"link": "https://www.douban.com/people/yujian-yujian/", "name": "\u9884\u89c1|| X X"}}, {"rating": "5", "vote_num": "279", "author": {"link": "https://www.douban.com/people/bighead/", "name": "\u5927\u5934\u7eff\u8c46"}}, {"rating": "1", "vote_num": "251", "author": {"link": "https://www.douban.com/people/Aragon/", "name": "mighty 4 dog"}}, {"rating": "1", "vote_num": "257", "author": {"link": "https://www.douban.com/people/leo1983/", "name": "\u65e0\u8bed\u6e05\u79cb"}}, {"rating": "2", "vote_num": "227", "author": {"link": "https://www.douban.com/people/3469533/", "name": "[\u5df2\u6ce8\u9500]"}}, {"rating": "3", "vote_num": "191", "author": {"link": "https://www.douban.com/people/anubis666/", "name": "Anubis"}}, {"rating": "3", "vote_num": "168", "author": {"link": "https://www.douban.com/people/A-sun/", "name": "A-sun*"}}, {"rating": "1", "vote_num": "153", "author": {"link": "https://www.douban.com/people/lihexi/", "name": "\u674e\u8377\u897f"}}, {"rating": "5", "vote_num": "138", "author": {"link": "https://www.douban.com/people/Cutebabyblue/", "name": "\u5355\u7ebf\u7a0b\u9752\u5e74"}}, {"rating": "3", "vote_num": "126", "author": {"link": "https://www.douban.com/people/heiheirage/", "name": "\u5d07\u5b50"}}, {"rating": "2", "vote_num": "110", "author": {"link": "https://www.douban.com/people/chenxizi/", "name": "\u8fb0\u66e6\u5b50"}}, {"rating": "5", "vote_num": "134", "author": {"link": "https://www.douban.com/people/su-su/", "name": "susu@23\u533a"}}, {"rating": "1", "vote_num": "100", "author": {"link": "https://www.douban.com/people/evich/", "name": "\u786c\u641e"}}, {"rating": "3", "vote_num": "100", "author": {"link": "https://www.douban.com/people/zyl622/", "name": "\u5bc2\u5730"}}, {"rating": "5", "vote_num": "78", "author": {"link": "https://www.douban.com/people/pan.c/", "name": "\u5927\u5152\u7ae5"}}, {"rating": "3", "vote_num": "33", "author": {"link": "https://www.douban.com/people/Uvo/", "name": "\u5e7d\u5c3e\u9e25"}}, {"rating": "undefined", "vote_num": "33", "author": {"link": "https://www.douban.com/people/1982059/", "name": "\u767d\u65e5\u68a6\u5148\u751f"}}, {"rating": "4", "vote_num": "32", "author": {"link": "https://www.douban.com/people/tianweiming/", "name": "Weiming"}}, {"rating": "4", "vote_num": "24", "author": {"link": "https://www.douban.com/people/felicitywyy/", "name": "\u738b\u5c0f\u90aa"}}, {"rating": "4", "vote_num": "9", "author": {"link": "https://www.douban.com/people/3540441/", "name": "\u540c\u5fd7\u4ea6\u51e1\u4eba\u4e2d\u6587\u7ad9"}}, {"rating": "3", "vote_num": "16", "author": {"link": "https://www.douban.com/people/tjz230/", "name": "\u5f71\u5fd7"}}, {"rating": "3", "vote_num": "8", "author": {"link": "https://www.douban.com/people/ballteda/", "name": "\u6389\u7ebf"}}, {"rating": "4", "vote_num": "11", "author": {"link": "https://www.douban.com/people/MECCA/", "name": "mecca(\u7f8e\u5361"}}, {"rating": "5", "vote_num": "1", "author": {"link": "https://www.douban.com/people/50165986/", "name": "\u955c\u82b1\u6c34\u6708"}}, {"rating": "3", "vote_num": "0", "author": {"link": "https://www.douban.com/people/outsider./", "name": "[\u5df2\u6ce8\u9500]"}}, {"rating": "5", "vote_num": "0", "author": {"link": "https://www.douban.com/people/kbs---ak/", "name": "\u642c\u7816\u5c11\u5e74"}}, {"rating": "4", "vote_num": "0", "author": {"link": "https://www.douban.com/people/51490972/", "name": "\u5f25\u8d5b\u4e9a\u4ee3\u8a00\u4eba"}}, {"rating": "4", "vote_num": "0", "author": {"link": "https://www.douban.com/people/corpse_929/", "name": "sonic monk"}}, {"rating": "4", "vote_num": "0", "author": {"link": "https://www.douban.com/people/Over5/", "name": "Over5"}}, {"rating": "5", "vote_num": "3", "author": {"link": "https://www.douban.com/people/mydear1011/", "name": "\u57ce\u5357\u8349\u6728\u751f"}}, {"rating": "4", "vote_num": "0", "author": {"link": "https://www.douban.com/people/3894772/", "name": "\u5c0f\u51a2ai\u827e"}}, {"rating": "undefined", "vote_num": "0", "author": {"link": "https://www.douban.com/people/56679235/", "name": "\u7a3b\u5b50\u9ea6\u7530"}}, {"rating": "4", "vote_num": "0", "author": {"link": "https://www.douban.com/people/mcPaul/", "name": "[\u5df2\u6ce8\u9500]"}}, {"rating": "4", "vote_num": "0", "author": {"link": "https://www.douban.com/people/51490972/", "name": "\u5f25\u8d5b\u4e9a\u4ee3\u8a00\u4eba"}}, {"rating": "4", "vote_num": "0", "author": {"link": "https://www.douban.com/people/corpse_929/", "name": "sonic monk"}}, {"rating": "4", "vote_num": "0", "author": {"link": "https://www.douban.com/people/Over5/", "name": "Over5"}}, {"rating": "5", "vote_num": "3", "author": {"link": "https://www.douban.com/people/mydear1011/", "name": "\u57ce\u5357\u8349\u6728\u751f"}}, {"rating": "4", "vote_num": "0", "author": {"link": "https://www.douban.com/people/3894772/", "name": "\u5c0f\u51a2ai\u827e"}}, {"rating": "undefined", "vote_num": "0", "author": {"link": "https://www.douban.com/people/56679235/", "name": "\u7a3b\u5b50\u9ea6\u7530"}}, {"rating": "4", "vote_num": "0", "author": {"link": "https://www.douban.com/people/mcPaul/", "name": "[\u5df2\u6ce8\u9500]"}}, {"rating": "5", "vote_num": "0", "author": {"link": "https://www.douban.com/people/sRain/", "name": "F\u00c9LIN"}}, {"rating": "4", "vote_num": "0", "author": {"link": "https://www.douban.com/people/35790692/", "name": "\u996e\u6b4c"}}, {"rating": "5", "vote_num": "0", "author": {"link": "https://www.douban.com/people/3387450/", "name": "\u5f3a\u5f3a"}}, {"rating": "5", "vote_num": "0", "author": {"link": "https://www.douban.com/people/Deepoxygen/", "name": "\u8d75\u7626\u5b50"}}, {"rating": "5", "vote_num": "0", "author": {"link": "https://www.douban.com/people/39233571/", "name": "\u6d85\u69c3"}}, {"rating": "4", "vote_num": "0", "author": {"link": "https://www.douban.com/people/rena.walker/", "name": "\u4e09\u6de1\u53d1"}}, {"rating": "4", "vote_num": "0", "author": {"link": "https://www.douban.com/people/rainelf1215/", "name": "Rainelf"}}, {"rating": "4", "vote_num": "0", "author": {"link": "https://www.douban.com/people/darlingtudai/", "name": "\u5218\u5c0f\u9edb"}}, {"rating": "3", "vote_num": "0", "author": {"link": "https://www.douban.com/people/Mrs.cherry/", "name": "\u751cm i l k \u3002"}}, {"rating": "4", "vote_num": "0", "author": {"link": "https://www.douban.com/people/word999/", "name": "word999"}}, {"rating": "5", "vote_num": "0", "author": {"link": "https://www.douban.com/people/suki_1001/", "name": "suki_1001"}}, {"rating": "5", "vote_num": "0", "author": {"link": "https://www.douban.com/people/4257314/", "name": "\u592a\u9971"}}, {"rating": "5", "vote_num": "0", "author": {"link": "https://www.douban.com/people/xingyier/", "name": "[\u5df2\u6ce8\u9500]"}}, {"rating": "4", "vote_num": "0", "author": {"link": "https://www.douban.com/people/rena.walker/", "name": "\u4e09\u6de1\u53d1"}}, {"rating": "4", "vote_num": "0", "author": {"link": "https://www.douban.com/people/rainelf1215/", "name": "Rainelf"}}, {"rating": "4", "vote_num": "0", "author": {"link": "https://www.douban.com/people/darlingtudai/", "name": "\u5218\u5c0f\u9edb"}}, {"rating": "3", "vote_num": "0", "author": {"link": "https://www.douban.com/people/Mrs.cherry/", "name": "\u751cm i l k \u3002"}}, {"rating": "4", "vote_num": "0", "author": {"link": "https://www.douban.com/people/word999/", "name": "word999"}}, {"rating": "5", "vote_num": "0", "author": {"link": "https://www.douban.com/people/suki_1001/", "name": "suki_1001"}}, {"rating": "5", "vote_num": "0", "author": {"link": "https://www.douban.com/people/4257314/", "name": "\u592a\u9971"}}, {"rating": "5", "vote_num": "0", "author": {"link": "https://www.douban.com/people/xingyier/", "name": "[\u5df2\u6ce8\u9500]"}}, {"rating": "5", "vote_num": "0", "author": {"link": "https://www.douban.com/people/4720825/", "name": "\u5eb7sisi"}}, {"rating": "5", "vote_num": "0", "author": {"link": "https://www.douban.com/people/apate/", "name": "\u627e\u51f9\u7684\u51f8"}}, {"rating": "5", "vote_num": "0", "author": {"link": "https://www.douban.com/people/35242331/", "name": "Kiddie"}}, {"rating": "4", "vote_num": "0", "author": {"link": "https://www.douban.com/people/mai_00/", "name": "\u9ea6"}}, {"rating": "4", "vote_num": "0", "author": {"link": "https://www.douban.com/people/rita034/", "name": "\u66ae\u9c7c\u6668\u5cab"}}, {"rating": "5", "vote_num": "0", "author": {"link": "https://www.douban.com/people/49002147/", "name": "\u963fKe"}}, {"rating": "5", "vote_num": "0", "author": {"link": "https://www.douban.com/people/mylittlebubu/", "name": "holasiyi"}}, {"rating": "5", "vote_num": "0", "author": {"link": "https://www.douban.com/people/young730/", "name": "\u7f8a\u5c0f\u82b1\u82b1\u82b1\u82b1"}}, {"rating": "4", "vote_num": "0", "author": {"link": "https://www.douban.com/people/blueboy2212/", "name": "\u84dd\u4eba"}}, {"rating": "5", "vote_num": "0", "author": {"link": "https://www.douban.com/people/cuican/", "name": "\u7480\u74a8"}}, {"rating": "3", "vote_num": "0", "author": {"link": "https://www.douban.com/people/doiwant/", "name": "doiwant"}}, {"rating": "undefined", "vote_num": "0", "author": {"link": "https://www.douban.com/people/shu9900/", "name": "\u6211\u7b49\u5c41\u6c11"}}, {"rating": "4", "vote_num": "0", "author": {"link": "https://www.douban.com/people/mai_00/", "name": "\u9ea6"}}, {"rating": "4", "vote_num": "0", "author": {"link": "https://www.douban.com/people/rita034/", "name": "\u66ae\u9c7c\u6668\u5cab"}}, {"rating": "5", "vote_num": "0", "author": {"link": "https://www.douban.com/people/49002147/", "name": "\u963fKe"}}, {"rating": "5", "vote_num": "0", "author": {"link": "https://www.douban.com/people/mylittlebubu/", "name": "holasiyi"}}, {"rating": "5", "vote_num": "0", "author": {"link": "https://www.douban.com/people/young730/", "name": "\u7f8a\u5c0f\u82b1\u82b1\u82b1\u82b1"}}, {"rating": "4", "vote_num": "0", "author": {"link": "https://www.douban.com/people/blueboy2212/", "name": "\u84dd\u4eba"}}, {"rating": "5", "vote_num": "0", "author": {"link": "https://www.douban.com/people/cuican/", "name": "\u7480\u74a8"}}, {"rating": "3", "vote_num": "0", "author": {"link": "https://www.douban.com/people/doiwant/", "name": "doiwant"}}, {"rating": "undefined", "vote_num": "0", "author": {"link": "https://www.douban.com/people/shu9900/", "name": "\u6211\u7b49\u5c41\u6c11"}}, {"rating": "5", "vote_num": "0", "author": {"link": "https://www.douban.com/people/Dev1antKoMi/", "name": "\u5f00\u98de\u673a\u7684\u8212\u514b.M"}}, {"rating": "4", "vote_num": "0", "author": {"link": "https://www.douban.com/people/49528832/", "name": "\u732b\u77e5\u9053"}}, {"rating": "4", "vote_num": "1", "author": {"link": "https://www.douban.com/people/sunnieorz/", "name": "\u4e14\u542c\u98ce\u541f"}}, {"rating": "5", "vote_num": "0", "author": {"link": "https://www.douban.com/people/seanhay/", "name": "\u772f\u772f\u773c\u4e60\u4e60"}}, {"rating": "5", "vote_num": "0", "author": {"link": "https://www.douban.com/people/victoria1202/", "name": "[\u5df2\u6ce8\u9500]"}}, {"rating": "4", "vote_num": "0", "author": {"link": "https://www.douban.com/people/xiaomumu0729/", "name": "\u8336\u549a\u8336\u549a\u8336"}}, {"rating": "5", "vote_num": "0", "author": {"link": "https://www.douban.com/people/anlexyu/", "name": "\u5403\u80f6\u5377\u7684Liz\u9e25"}}, {"rating": "5", "vote_num": "0", "author": {"link": "https://www.douban.com/people/2656189/", "name": "poisson"}}, {"rating": "5", "vote_num": "0", "author": {"link": "https://www.douban.com/people/xxliang/", "name": "XX\u4eae"}}, {"rating": "5", "vote_num": "0", "author": {"link": "https://www.douban.com/people/weilaipsalms/", "name": "\u5f20\u672a\u6765"}}, {"rating": "5", "vote_num": "0", "author": {"link": "https://www.douban.com/people/Butlerliu/", "name": "Butler"}}, {"rating": "4", "vote_num": "1", "author": {"link": "https://www.douban.com/people/sunnieorz/", "name": "\u4e14\u542c\u98ce\u541f"}}, {"rating": "5", "vote_num": "0", "author": {"link": "https://www.douban.com/people/seanhay/", "name": "\u772f\u772f\u773c\u4e60\u4e60"}}, {"rating": "5", "vote_num": "0", "author": {"link": "https://www.douban.com/people/victoria1202/", "name": "[\u5df2\u6ce8\u9500]"}}, {"rating": "4", "vote_num": "0", "author": {"link": "https://www.douban.com/people/xiaomumu0729/", "name": "\u8336\u549a\u8336\u549a\u8336"}}, {"rating": "5", "vote_num": "0", "author": {"link": "https://www.douban.com/people/anlexyu/", "name": "\u5403\u80f6\u5377\u7684Liz\u9e25"}}, {"rating": "5", "vote_num": "0", "author": {"link": "https://www.douban.com/people/2656189/", "name": "poisson"}}, {"rating": "5", "vote_num": "0", "author": {"link": "https://www.douban.com/people/xxliang/", "name": "XX\u4eae"}}, {"rating": "5", "vote_num": "0", "author": {"link": "https://www.douban.com/people/weilaipsalms/", "name": "\u5f20\u672a\u6765"}}, {"rating": "5", "vote_num": "0", "author": {"link": "https://www.douban.com/people/Butlerliu/", "name": "Butler"}}, {"rating": "5", "vote_num": "0", "author": {"link": "https://www.douban.com/people/finalx/", "name": "maomao"}}, {"rating": "4", "vote_num": "0", "author": {"link": "https://www.douban.com/people/xiulan/", "name": "\u7b71\u84dd"}}, {"rating": "5", "vote_num": "0", "author": {"link": "https://www.douban.com/people/msxinran/", "name": "\u6b46\u7136"}}, {"rating": "4", "vote_num": "0", "author": {"link": "https://www.douban.com/people/42623950/", "name": "\u516b\u6708\u5fae\u5149"}}, {"rating": "5", "vote_num": "0", "author": {"link": "https://www.douban.com/people/46180980/", "name": "EVA_\u5f81\u670d\u5929\u5802"}}, {"rating": "5", "vote_num": "0", "author": {"link": "https://www.douban.com/people/jolinalbert/", "name": "\u5723\u65e0\u5e38"}}, {"rating": "5", "vote_num": "0", "author": {"link": "https://www.douban.com/people/louxing/", "name": "\u4e0e\u5f71\u7275\u624b"}}, {"rating": "5", "vote_num": "0", "author": {"link": "https://www.douban.com/people/amorjolly/", "name": "\u7231\u8309\u7eff\u7eff"}}, {"rating": "undefined", "vote_num": "0", "author": {"link": "https://www.douban.com/people/chaoluyun/", "name": "\u5361\u96de\u99ac"}}, {"rating": "3", "vote_num": "0", "author": {"link": "https://www.douban.com/people/floathwusu/", "name": "\u9ec4\u65e0\u82cf"}}, {"rating": "4", "vote_num": "0", "author": {"link": "https://www.douban.com/people/ocean_kwai/", "name": "\u6218\u56fd\u5ba2"}}, {"rating": "5", "vote_num": "0", "author": {"link": "https://www.douban.com/people/jolinalbert/", "name": "\u5723\u65e0\u5e38"}}, {"rating": "5", "vote_num": "0", "author": {"link": "https://www.douban.com/people/louxing/", "name": "\u4e0e\u5f71\u7275\u624b"}}, {"rating": "5", "vote_num": "0", "author": {"link": "https://www.douban.com/people/amorjolly/", "name": "\u7231\u8309\u7eff\u7eff"}}, {"rating": "undefined", "vote_num": "0", "author": {"link": "https://www.douban.com/people/chaoluyun/", "name": "\u5361\u96de\u99ac"}}, {"rating": "3", "vote_num": "0", "author": {"link": "https://www.douban.com/people/floathwusu/", "name": "\u9ec4\u65e0\u82cf"}}, {"rating": "4", "vote_num": "0", "author": {"link": "https://www.douban.com/people/ocean_kwai/", "name": "\u6218\u56fd\u5ba2"}}, {"rating": "4", "vote_num": "0", "author": {"link": "https://www.douban.com/people/1567067/", "name": "\u5180\u7167\u5bdc"}}, {"rating": "4", "vote_num": "0", "author": {"link": "https://www.douban.com/people/xiaodiutan/", "name": "beborn"}}, {"rating": "5", "vote_num": "0", "author": {"link": "https://www.douban.com/people/1555955/", "name": "shaguaYIg"}}, {"rating": "4", "vote_num": "0", "author": {"link": "https://www.douban.com/people/xygoing/", "name": "\u859b\u6613"}}, {"rating": "4", "vote_num": "0", "author": {"link": "https://www.douban.com/people/1532705/", "name": "blb"}}, {"rating": "5", "vote_num": "0", "author": {"link": "https://www.douban.com/people/huasuoepc/", "name": "\u5c0f\u5c0f\u767d\u836f\u4e0d\u80fd\u505c"}}, {"rating": "5", "vote_num": "0", "author": {"link": "https://www.douban.com/people/tuosai/", "name": "\u6258\u816e"}}, {"rating": "5", "vote_num": "0", "author": {"link": "https://www.douban.com/people/Gaarafly/", "name": "Luka"}}, {"rating": "2", "vote_num": "0", "author": {"link": "https://www.douban.com/people/terababy/", "name": "terababy"}}, {"rating": "4", "vote_num": "0", "author": {"link": "https://www.douban.com/people/lilylillylillie/", "name": "ly\u8389"}}, {"rating": "5", "vote_num": "0", "author": {"link": "https://www.douban.com/people/chrisdoga/", "name": "\u514b\u91cc\u65af\u6735\u560e"}}, {"rating": "4", "vote_num": "0", "author": {"link": "https://www.douban.com/people/xisahala/", "name": "i"}}, {"rating": "2", "vote_num": "0", "author": {"link": "https://www.douban.com/people/godblesswho/", "name": "\u9811\u5f37\u7684C"}}, {"rating": "5", "vote_num": "0", "author": {"link": "https://www.douban.com/people/wangzhiyan1987/", "name": "\u4e4b\u5f66"}}, {"rating": "5", "vote_num": "0", "author": {"link": "https://www.douban.com/people/chrisdoga/", "name": "\u514b\u91cc\u65af\u6735\u560e"}}, {"rating": "4", "vote_num": "0", "author": {"link": "https://www.douban.com/people/xisahala/", "name": "i"}}, {"rating": "2", "vote_num": "0", "author": {"link": "https://www.douban.com/people/godblesswho/", "name": "\u9811\u5f37\u7684C"}}, {"rating": "5", "vote_num": "0", "author": {"link": "https://www.douban.com/people/wangzhiyan1987/", "name": "\u4e4b\u5f66"}}, {"rating": "4", "vote_num": "0", "author": {"link": "https://www.douban.com/people/BlindwolfHyn/", "name": "\u5357\u570b\u7d05\u8c46\u5317\u570b\u67b3"}}, {"rating": "5", "vote_num": "0", "author": {"link": "https://www.douban.com/people/rollin/", "name": "\u53c9\u53c9\u5c0f\u7bad\u732a"}}, {"rating": "4", "vote_num": "0", "author": {"link": "https://www.douban.com/people/quanquan0817/", "name": "\u5416\u76ae\u7403"}}, {"rating": "5", "vote_num": "0", "author": {"link": "https://www.douban.com/people/2859691/", "name": "\u6700\u70e6\u88c5\u903c"}}, {"rating": "5", "vote_num": "0", "author": {"link": "https://www.douban.com/people/xcf1994/", "name": "\u50b2\u5a07\u7eed\u5c0f\u80a5"}}, {"rating": "4", "vote_num": "0", "author": {"link": "https://www.douban.com/people/asdoherty/", "name": "asdoherty"}}, {"rating": "5", "vote_num": "0", "author": {"link": "https://www.douban.com/people/MagicK/", "name": "\u9ea6\u5c0f\u767d"}}, {"rating": "5", "vote_num": "0", "author": {"link": "https://www.douban.com/people/ruilixiurui/", "name": "\u9510\u5229\u4fee\u854a"}}, {"rating": "1", "vote_num": "0", "author": {"link": "https://www.douban.com/people/NG/", "name": "NG"}}, {"rating": "4", "vote_num": "0", "author": {"link": "https://www.douban.com/people/bobozang/", "name": "[\u5df2\u6ce8\u9500]"}}, {"rating": "5", "vote_num": "0", "author": {"link": "https://www.douban.com/people/45826774/", "name": "\u963f\u5e03\u8c46"}}, {"rating": "5", "vote_num": "0", "author": {"link": "https://www.douban.com/people/liuqing2009/", "name": "\u5218\u5c0f\u9752"}}, {"rating": "5", "vote_num": "0", "author": {"link": "https://www.douban.com/people/littletwo/", "name": "littletwo"}}, {"rating": "5", "vote_num": "0", "author": {"link": "https://www.douban.com/people/4108269/", "name": "TiantianLi"}}, {"rating": "5", "vote_num": "0", "author": {"link": "https://www.douban.com/people/3772330/", "name": "\u950b"}}, {"rating": "5", "vote_num": "0", "author": {"link": "https://www.douban.com/people/fotoz/", "name": "\u8131\u7f30\u7684\u65fa\u8ca1"}}, {"rating": "5", "vote_num": "0", "author": {"link": "https://www.douban.com/people/45826774/", "name": "\u963f\u5e03\u8c46"}}, {"rating": "5", "vote_num": "0", "author": {"link": "https://www.douban.com/people/liuqing2009/", "name": "\u5218\u5c0f\u9752"}}, {"rating": "5", "vote_num": "0", "author": {"link": "https://www.douban.com/people/littletwo/", "name": "littletwo"}}, {"rating": "5", "vote_num": "0", "author": {"link": "https://www.douban.com/people/4108269/", "name": "TiantianLi"}}, {"rating": "5", "vote_num": "0", "author": {"link": "https://www.douban.com/people/3772330/", "name": "\u950b"}}, {"rating": "5", "vote_num": "0", "author": {"link": "https://www.douban.com/people/fotoz/", "name": "\u8131\u7f30\u7684\u65fa\u8ca1"}}, {"rating": "5", "vote_num": "0", "author": {"link": "https://www.douban.com/people/ostrich_lady/", "name": "\u9d15\u9ce5\u5c0f\u59d0"}}, {"rating": "5", "vote_num": "0", "author": {"link": "https://www.douban.com/people/44021817/", "name": "Moriarty"}}, {"rating": "4", "vote_num": "0", "author": {"link": "https://www.douban.com/people/Emo_K/", "name": "\u94f6\u6cb3\u516c\u56ed"}}, {"rating": "4", "vote_num": "0", "author": {"link": "https://www.douban.com/people/54274563/", "name": "\u9ae6\u9ae6"}}, {"rating": "5", "vote_num": "0", "author": {"link": "https://www.douban.com/people/lareine/", "name": "\u8336\u8336"}}, {"rating": "5", "vote_num": "0", "author": {"link": "https://www.douban.com/people/yingjoy/", "name": "\u5de6\u557e\u557e"}}, {"rating": "5", "vote_num": "0", "author": {"link": "https://www.douban.com/people/bchbsw/", "name": "\u5de6\u5973\u53f3\u5355"}}, {"rating": "4", "vote_num": "0", "author": {"link": "https://www.douban.com/people/Castellan199/", "name": "\u840c . \u674e"}}, {"rating": "5", "vote_num": "0", "author": {"link": "https://www.douban.com/people/jshippo/", "name": "\u5927\u6cb3\u9a6c"}}, {"rating": "undefined", "vote_num": "0", "author": {"link": "https://www.douban.com/people/34495652/", "name": "\u5824\u5951\u8bfa\u7684\u4e9a\u514b\u529b"}}, {"rating": "5", "vote_num": "0", "author": {"link": "https://www.douban.com/people/3266143/", "name": "\u83ab\u4e91\u8f69"}}, {"rating": "5", "vote_num": "0", "author": {"link": "https://www.douban.com/people/23450183/", "name": "\u590f\u5929De\u897f\u74dc"}}, {"rating": "4", "vote_num": "0", "author": {"link": "https://www.douban.com/people/liebsteprettywa/", "name": "\u535a\u535a\u7ef4\u5947"}}, {"rating": "5", "vote_num": "0", "author": {"link": "https://www.douban.com/people/lhchanchen/", "name": "HALO\u672a\u6765"}}, {"rating": "undefined", "vote_num": "0", "author": {"link": "https://www.douban.com/people/34495652/", "name": "\u5824\u5951\u8bfa\u7684\u4e9a\u514b\u529b"}}, {"rating": "5", "vote_num": "0", "author": {"link": "https://www.douban.com/people/3266143/", "name": "\u83ab\u4e91\u8f69"}}, {"rating": "5", "vote_num": "0", "author": {"link": "https://www.douban.com/people/23450183/", "name": "\u590f\u5929De\u897f\u74dc"}}, {"rating": "4", "vote_num": "0", "author": {"link": "https://www.douban.com/people/liebsteprettywa/", "name": "\u535a\u535a\u7ef4\u5947"}}, {"rating": "5", "vote_num": "0", "author": {"link": "https://www.douban.com/people/lhchanchen/", "name": "HALO\u672a\u6765"}}, {"rating": "3", "vote_num": "0", "author": {"link": "https://www.douban.com/people/3355859/", "name": "REX"}}, {"rating": "5", "vote_num": "0", "author": {"link": "https://www.douban.com/people/bbznj/", "name": "\u820c\u5c16\u4e0a\u7684\u732a\u4e48\u4e48"}}, {"rating": "3", "vote_num": "0", "author": {"link": "https://www.douban.com/people/yeshunjia/", "name": "\u5357\u689d\u67d0\u8449"}}, {"rating": "4", "vote_num": "0", "author": {"link": "https://www.douban.com/people/j_today/", "name": "\u5f02\u4e16\u7eff"}}, {"rating": "4", "vote_num": "0", "author": {"link": "https://www.douban.com/people/stanley.kerry/", "name": "Kerry\u2122"}}, {"rating": "5", "vote_num": "0", "author": {"link": "https://www.douban.com/people/galina/", "name": "\u5496\u55b1\u5a1c"}}, {"rating": "5", "vote_num": "0", "author": {"link": "https://www.douban.com/people/adel/", "name": "\u9648\u5c0f\u6843"}}, {"rating": "5", "vote_num": "0", "author": {"link": "https://www.douban.com/people/onshuway/", "name": "\u5c0f\u8033\u6735\u56fe\u5417"}}, {"rating": "5", "vote_num": "0", "author": {"link": "https://www.douban.com/people/no350028/", "name": "\u5927\u661f"}}, {"rating": "undefined", "vote_num": "0", "author": {"link": "https://www.douban.com/people/April_yang/", "name": "\u5b89\u9759\u7684\u6162\u9633\u5149"}}, {"rating": "5", "vote_num": "0", "author": {"link": "https://www.douban.com/people/colejie/", "name": "\u72d7\u5a03\u5c71\u4e0b\u4e00\u68f5\u8349"}}, {"rating": "5", "vote_num": "0", "author": {"link": "https://www.douban.com/people/hiddenIris/", "name": "Tes\u3002"}}, {"rating": "5", "vote_num": "0", "author": {"link": "https://www.douban.com/people/anxiaojie/", "name": "\u5b89\u5c0f\u6d01"}}, {"rating": "4", "vote_num": "0", "author": {"link": "https://www.douban.com/people/43732610/", "name": "wdzy"}}, {"rating": "5", "vote_num": "0", "author": {"link": "https://www.douban.com/people/cc0803/", "name": "\u4ece\u524d\u6709\u4e00\u53ea\u8003\u62c9"}}], "information": {"language": ["\u65e5\u8bed"], "country": ["\u65e5\u672c"], "actor": ["\u8fb0\u5df1\u52aa", "\u767d\u77f3\u7eeb\u4e43", "\u5fd7\u4e43\u539f\u826f\u5b50", "\u5c71\u53e3\u6731\u7f8e", "\u7aef\u7530\u5b8f\u4e09"], "director": ["\u9ad8\u7551\u52cb"], "alias": ["\u518d\u89c1\u8424\u706b\u866b(\u6e2f) ", " \u8424\u706b\u633d\u6b4c ", " \u706b\u5e18\u4e4b\u5893 ", " Hotaru no haka ", " Tombstone for Fireflies ", " Grave of the Fireflies ", " Tomb of the Fireflies"], "length": ["89 \u5206\u949f"], "imdb": "http://www.imdb.com/title/tt0095327", "time": ["1988-04-16(\u65e5\u672c)"], "type": ["\u5267\u60c5", "\u52a8\u753b", "\u6218\u4e89"], "screenwriter": ["\u9ad8\u7551\u52cb", "\u91ce\u5742\u662d\u5982"]}, "photo": [{"src": "https://img3.doubanio.com/view/photo/albumicon/public/p992023361.jpg", "alt": "\u56fe\u7247", "ref": "https://movie.douban.com/photos/photo/992023361/"}, {"src": "https://img3.doubanio.com/view/photo/albumicon/public/p2190939005.jpg", "alt": "\u56fe\u7247", "ref": "https://movie.douban.com/photos/photo/2190939005/"}, {"src": "https://img3.doubanio.com/view/photo/albumicon/public/p1809560336.jpg", "alt": "\u56fe\u7247", "ref": "https://movie.douban.com/photos/photo/1809560336/"}, {"src": "https://img1.doubanio.com/view/photo/albumicon/public/p456682817.jpg", "alt": "\u56fe\u7247", "ref": "https://movie.douban.com/photos/photo/456682817/"}, {"src": "https://img1.doubanio.com/view/photo/albumicon/public/p456680958.jpg", "alt": "\u56fe\u7247", "ref": "https://movie.douban.com/photos/photo/456680958/"}], "name": "\u8424\u706b\u866b\u4e4b\u5893 \u706b\u5782\u308b\u306e\u5893", "poster": ["https://img1.doubanio.com/view/movie_poster_cover/ipst/public/p1157334208.jpg"], "review": [{"rating": "4", "author": {"link": "https://www.douban.com/people/CammyWhite/", "name": "\u2605\u2606\u2606\u2606\u2606"}, "title": {"link": "https://movie.douban.com/review/1414209/", "name": "\u6279\u5224\u300a\u518d\u89c1\u8424\u706b\u866b\u300b"}}, {"rating": "1", "author": {"link": "https://www.douban.com/people/21260782/", "name": "\u571f\u8c46"}, "title": {"link": "https://movie.douban.com/review/3374935/", "name": "\u5267\u900f\uff1a\u6211\u662f\u600e\u4e48\u628a\u59b9\u59b9\u517b\u6b7b\u7684"}}, {"rating": "4", "author": {"link": "https://www.douban.com/people/ridden/", "name": "Ridden"}, "title": {"link": "https://movie.douban.com/review/1438543/", "name": "\u62dc\u6258\uff0c\u4e0d\u662f\u5bab\u5d0e\u5cfb\uff0c\u662f\u9ad8\u7551\u52cb\uff01"}}, {"rating": "5", "author": {"link": "https://www.douban.com/people/2317516/", "name": "\u6555\u52d2\u6b4c"}, "title": {"link": "https://movie.douban.com/review/1612634/", "name": "\u8424\u706b\u866b\u6f2b\u5929\uff0c\u5c0f\u65e5\u672c\u611f\u52a8\u4e86\u6211"}}, {"rating": "1", "author": {"link": "https://www.douban.com/people/haigt/", "name": "\u5c0f\u9ed1"}, "title": {"link": "https://movie.douban.com/review/3128632/", "name": "\u6211\u4e0d\u80fd\u7406\u89e3\u4e3a\u4ec0\u4e48\u6709\u4eba\u8981\u54ed"}}, {"rating": "2", "author": {"link": "https://www.douban.com/people/young753951/", "name": "young"}, "title": {"link": "https://movie.douban.com/review/2070124/", "name": "\u8ba9\u6211\u8bf4\u4e9b\u4ec0\u4e48\u5462\uff01"}}, {"rating": "5", "author": {"link": "https://www.douban.com/people/1655072/", "name": "migi"}, "title": {"link": "https://movie.douban.com/review/1178505/", "name": "\u4e27\u949f\u4e3a\u4f55\u800c\u9e23"}}, {"rating": "5", "author": {"link": "https://www.douban.com/people/1261986/", "name": "\u5deb\u5c71\u96e8\u5e08"}, "title": {"link": "https://movie.douban.com/review/2313972/", "name": "\u7231\u662f\u5982\u6b64\u56f0\u96be"}}, {"rating": "5", "author": {"link": "https://www.douban.com/people/2488086/", "name": "mosquito"}, "title": {"link": "https://movie.douban.com/review/1886121/", "name": "\u6211\u4eec\u539f\u8c05\u7684\u662f\u8ba4\u9519\u7684\u4eba"}}, {"rating": "5", "author": {"link": "https://www.douban.com/people/emor-hwang/", "name": "MJ\u00d8LK"}, "title": {"link": "https://movie.douban.com/review/1940184/", "name": "\u7247\u5b50\u662f\u62ff\u4f86\u6b23\u8cde\u7684\uff0c\u8acb\u52ff\u4e82\u5410\u201c\u653f\u6cbb\u53e3\u6c34\u201d\uff01"}}, {"rating": "3", "author": {"link": "https://www.douban.com/people/hamturi/", "name": "\u7fc1\u5c0f\u6837"}, "title": {"link": "https://movie.douban.com/review/1477867/", "name": "\u4e00\u534a\u5927\u73af\u5883\u4e00\u534a\u81ea\u4f5c\u5b7d"}}, {"rating": "5", "author": {"link": "https://www.douban.com/people/papillon/", "name": "Lena"}, "title": {"link": "https://movie.douban.com/review/1012171/", "name": "\u6b8b\u9177~~"}}, {"rating": "1", "author": {"link": "https://www.douban.com/people/58035060/", "name": "\u9644\u79bb"}, "title": {"link": "https://movie.douban.com/review/5450445/", "name": "\u770b\u7740\u8fd9\u54e5\u5c31\u706b\u5927"}}, {"rating": "2", "author": {"link": "https://www.douban.com/people/57701070/", "name": "\u84ee"}, "title": {"link": "https://movie.douban.com/review/5545981/", "name": "\u54ea\u91cc\u8ba9\u4eba\u611f\u52a8\u4e86"}}, {"rating": "5", "author": {"link": "https://www.douban.com/people/bychance/", "name": "bychance"}, "title": {"link": "https://movie.douban.com/review/1216497/", "name": "\u4e0d\u60f3\u8bf4\u518d\u89c1"}}, {"rating": "1", "author": {"link": "https://www.douban.com/people/Mr.Grey/", "name": "filippopl"}, "title": {"link": "https://movie.douban.com/review/2039167/", "name": "\u53bb\u4f60\u5988\u7684\u8424\u706b\u866b\uff01"}}, {"rating": "1", "author": {"link": "https://www.douban.com/people/2194417/", "name": "\u98ce\u548c\u65e5\u4e3d\u7684\u65e5\u5b50"}, "title": {"link": "https://movie.douban.com/review/1289812/", "name": "\u65bd\u5bb3\u8005\u6447\u8eab\u4e00\u53d8\u6210\u4e86\u88ab\u5bb3\u8005\uff01\u5f00\u4ec0\u4e48\u73a9\u7b11\uff01\u5b58\u4ec0\u4e48\u5fc3\uff01"}}, {"rating": "5", "author": {"link": "https://www.douban.com/people/44832442/", "name": "LADY MM"}, "title": {"link": "https://movie.douban.com/review/7631959/", "name": "\u5144\u59b9\u7684\u6b7b\u4ea1\u4e2d\u95f4\u63d2\u5165\u4e86\u7f8e\u597d\u771f\u5b9e"}}, {"rating": "1", "author": {"link": "https://www.douban.com/people/40926788/", "name": "Panther"}, "title": {"link": "https://movie.douban.com/review/3476876/", "name": "\u7c89\u9970\u6218\u4e89\u7684\u70c2\u7247"}}, {"rating": "4", "author": {"link": "https://www.douban.com/people/37997521/", "name": "\u8d1d\u5229\u5361"}, "title": {"link": "https://movie.douban.com/review/3147852/", "name": "\u4e0d\u9020\u4f5c\u521a\u521a\u597d"}}, {"rating": "3", "author": {"link": "https://www.douban.com/people/xuwen0104/", "name": "\u963f\u80da"}, "title": {"link": "https://movie.douban.com/review/5765968/", "name": "\u963f\u59e8\u9a82\u5f97\u597d\u3002"}}, {"rating": "5", "author": {"link": "https://www.douban.com/people/coluber/", "name": "Coluber"}, "title": {"link": "https://movie.douban.com/review/3430251/", "name": "\u8fd9\u662f\u4e00\u90e8\u201c\u5c0f\u201d\u7535\u5f71"}}, {"rating": "1", "author": {"link": "https://www.douban.com/people/37832420/", "name": "piggy"}, "title": {"link": "https://movie.douban.com/review/7450903/", "name": "\u4ece\u7acb\u610f\u5230\u5236\u4f5c\u4e00\u65e0\u662f\u5904\u7684\u7247\u5b50\u3002"}}, {"rating": "1", "author": {"link": "https://www.douban.com/people/september-/", "name": "sep"}, "title": {"link": "https://movie.douban.com/review/5009385/", "name": "\u7247\u9762\u7684\u89c6\u89d2"}}, {"rating": "2", "author": {"link": "https://www.douban.com/people/dalianhaizao/", "name": "\u8c22\u4e4b\u827e"}, "title": {"link": "https://movie.douban.com/review/7428499/", "name": "\u6211\u4eec\u4e0d\u5e94\u8be5\u540c\u60c5\uff0c\u800c\u5e94\u8be5\u8b66\u60d5\u3002"}}, {"rating": "4", "author": {"link": "https://www.douban.com/people/47719620/", "name": "chiller"}, "title": {"link": "https://movie.douban.com/review/4871434/", "name": "\u522b\u8ba9\u8bc4\u4ef7\u4ec0\u4e48\u7684\u5f71\u54cd\u4f60\u554a"}}, {"rating": "1", "author": {"link": "https://www.douban.com/people/46594184/", "name": "\u6709\u4e2a\u83dc\u83dc\u5b50"}, "title": {"link": "https://movie.douban.com/review/6240218/", "name": "\u6700\u538c\u6076\u7684\u4e00\u90e8\u65e5\u672c\u52a8\u753b\u3002"}}, {"rating": "4", "author": {"link": "https://www.douban.com/people/arista/", "name": "\u65e5\u843d\u9152\u9986"}, "title": {"link": "https://movie.douban.com/review/1050785/", "name": "\u518d\u89c1\uff0c\u8424\u706b\u866b"}}, {"rating": "5", "author": {"link": "https://www.douban.com/people/kwan/", "name": "\u95a2\u95a2\u95a2\u95a2\u95a2\u95a2\uff01"}, "title": {"link": "https://movie.douban.com/review/1039921/", "name": "\u662d\u548c20\u5e749\u670821\u65e5\uff0c\u6211\u6b7b\u4e86\u3002"}}, {"rating": "1", "author": {"link": "https://www.douban.com/people/49915657/", "name": "\u6df1\u84dd"}, "title": {"link": "https://movie.douban.com/review/5268447/", "name": "\u4e00\u6ef4\u773c\u6cea\u7684\u7acb\u573a"}}, {"rating": "1", "author": {"link": "https://www.douban.com/people/12125538/", "name": "forwhat"}, "title": {"link": "https://movie.douban.com/review/3123397/", "name": "\u8fd9\u662f\u4e00\u90e8\u6709\u7279\u6b8a\u76ee\u7684\u7684\u7535\u5f71"}}, {"rating": "3", "author": {"link": "https://www.douban.com/people/37803987/", "name": "\u5706\u6ee1\u91d1\u79cb"}, "title": {"link": "https://movie.douban.com/review/7546675/", "name": "\u4eba\u6027\u7684\u51b7\u6f20\u662f\u53e6\u4e00\u573a\u6218\u4e89"}}, {"rating": "3", "author": {"link": "https://www.douban.com/people/maplerubbish/", "name": "\u4e00\u4e5d\u516b\u53c9"}, "title": {"link": "https://movie.douban.com/review/5799016/", "name": "\u4e00\u70b9\u611f\u60f3"}}, {"rating": "1", "author": {"link": "https://www.douban.com/people/ludanme/", "name": "\u5364\u86cb"}, "title": {"link": "https://movie.douban.com/review/5466455/", "name": "\u56fd\u4eba\u5f88\u5f31\u667a"}}, {"rating": "4", "author": {"link": "https://www.douban.com/people/3065025/", "name": "\u5927\u5934\u9c7c"}, "title": {"link": "https://movie.douban.com/review/3141814/", "name": "\u8bf7\u4e0d\u8981\u4f2a\u88c5\u6210\u53d7\u5bb3\u8005\u7684\u6837\u5b50"}}, {"rating": "3", "author": {"link": "https://www.douban.com/people/1643495/", "name": "gao"}, "title": {"link": "https://movie.douban.com/review/1475237/", "name": "\u96be\u53d7"}}, {"rating": "1", "author": {"link": "https://www.douban.com/people/3686271/", "name": "\u5fa1\u9675\u5fa1\u5f71"}, "title": {"link": "https://movie.douban.com/review/6489660/", "name": "\u6211\u65e0\u6cd5\u628a\u6211\u7684\u6cea\u6c34\u732e\u7ed9\u65bd\u5bb3\u8005"}}, {"rating": "1", "author": {"link": "https://www.douban.com/people/shcalm/", "name": "\u609f\u996d\u6253\u68d2\u7403"}, "title": {"link": "https://movie.douban.com/review/2120079/", "name": "\u65e0\u6cd5\u5168\u8eab\u5fc3\u7684\u770b"}}, {"rating": "3", "author": {"link": "https://www.douban.com/people/66339171/", "name": "komalotwo"}, "title": {"link": "https://movie.douban.com/review/6492102/", "name": "\u867d\u7136\u5f88\u611f\u52a8\uff0c\u4f46\u662f\u6211\u8fd8\u662f\u8981\u5410\u69fd\u8fd9\u4e2a\u4f5c\u6b7b\u7684\u54e5\u54e5\u3002\u3002"}}, {"rating": "5", "author": {"link": "https://www.douban.com/people/1118655/", "name": "Guide"}, "title": {"link": "https://movie.douban.com/review/2310788/", "name": "\u5982\u679c\u6709\u5929\u5802\u53ef\u4ee5\u91cd\u9047"}}, {"rating": "5", "author": {"link": "https://www.douban.com/people/2891116/", "name": "\u8336\u96e8\u98ce"}, "title": {"link": "https://movie.douban.com/review/1884451/", "name": "\u6f2b\u5929\u8424\u706b\u2014\u2014\u591c\u6df1\u4e86\uff0c\u5feb\u4e9b\u7761\u5427"}}, {"rating": "4", "author": {"link": "https://www.douban.com/people/1462465/", "name": "kusicat"}, "title": {"link": "https://movie.douban.com/review/1510688/", "name": "\u4e16\u754c\u4e3b\u4e49 \u6291\u6216 \u6c11\u65cf\u4e3b\u4e49"}}, {"rating": "5", "author": {"link": "https://www.douban.com/people/shayxu/", "name": "[\u5df2\u6ce8\u9500]"}, "title": {"link": "https://movie.douban.com/review/1398352/", "name": "\u6211\u53d1\u73b0\u300a\u65b0\u4e4c\u9f99\u9662\u300b\u91cc\u90a3\u4e9b\u4eba\u770b\u7684\u662f\u4ec0\u4e48\u7535\u5f71\u4e86"}}, {"rating": "4", "author": {"link": "https://www.douban.com/people/alcudish/", "name": "\u80a5\u561f\u561f\u5de6\u536b\u95e8"}, "title": {"link": "https://movie.douban.com/review/1361357/", "name": "\u770b\u4e86\u4f1a\u90c1\u95f7\u7684\u52a8\u753b\u7247"}}, {"rating": "1", "author": {"link": "https://www.douban.com/people/71954665/", "name": "sicilia77"}, "title": {"link": "https://movie.douban.com/review/5918599/", "name": "\u65e5\u672c\u7684\u4fb5\u534e\u6218\u573a---\u4e2d\u56fd\u4e09\u5343\u4e07\u7684\u4ea1\u7075"}}, {"rating": "2", "author": {"link": "https://www.douban.com/people/27433660/", "name": "woody"}, "title": {"link": "https://movie.douban.com/review/5630763/", "name": "\u5931\u671b\u4e4b\u6781\uff0c\u6124\u6012\u4e86\u534a\u4e0a\u5348"}}, {"rating": "4", "author": {"link": "https://www.douban.com/people/randidianying/", "name": "\u5189\u7b1b"}, "title": {"link": "https://movie.douban.com/review/2890657/", "name": "\u4e00\u4e2a\u5c0f\u7537\u5b69\u5728\u6218\u4e71\u4e2d\u8c31\u5199\u7684\u300a\u8424\u706b\u633d\u6b4c\u300b"}}, {"rating": "4", "author": {"link": "https://www.douban.com/people/greenrabbit/", "name": "\u8309\u8389\u5fae\u8a00"}, "title": {"link": "https://movie.douban.com/review/1934251/", "name": "\u4e0d\u8fc7\u53ea\u662f\u4e00\u573a\u81ea\u6211\u575a\u6301"}}, {"rating": "3", "author": {"link": "https://www.douban.com/people/3512233/", "name": "\u84dd\u51b0"}, "title": {"link": "https://movie.douban.com/review/1628384/", "name": "\u4e0d\u662f\u5f88\u559c\u6b22\u8fd9\u90e8\u4f5c\u54c1"}}, {"rating": "5", "author": {"link": "https://www.douban.com/people/119942332/", "name": "\u80a5\u561f\u561f\u53f3\u536b\u95e8"}, "title": {"link": "https://movie.douban.com/review/8083096/", "name": "\u81f4\u6240\u6709\u8bc41\u5206\u7684\u4eba"}}, {"rating": "4", "author": {"link": "https://www.douban.com/people/56274081/", "name": "\u6657 \u7ffe"}, "title": {"link": "https://movie.douban.com/review/6305273/", "name": "\u6d3b\u4e0b\u53bb\uff0c\u5f88\u7b80\u5355\u5374\u4e5f\u5f88\u96be"}}, {"rating": "2", "author": {"link": "https://www.douban.com/people/53977796/", "name": "\u7761\u4e0d\u9192\u7684\u6df7\u86cb"}, "title": {"link": "https://movie.douban.com/review/5607089/", "name": "\u770b\u5b8c\u6ca1\u6709\u611f\u52a8\u53ea\u6709\u6df1\u6df1\u7684\u538c\u6076"}}, {"rating": "3", "author": {"link": "https://www.douban.com/people/4589304/", "name": "\u9c7c\u6765\u5982\u6b64"}, "title": {"link": "https://movie.douban.com/review/2350429/", "name": "\u8424\u706b\u866b\u4e4b\u5893"}}, {"rating": "2", "author": {"link": "https://www.douban.com/people/1173776/", "name": "ufomaker"}, "title": {"link": "https://movie.douban.com/review/1786121/", "name": "\u5982\u6897\u5728\u5589"}}, {"rating": "5", "author": {"link": "https://www.douban.com/people/2569949/", "name": "\u590f\u81f3"}, "title": {"link": "https://movie.douban.com/review/1470879/", "name": "\u6211\u4eec\u90fd\u662f\u7cd6\uff0c\u751c\u5230\u5fe7\u4f24\u00b7\u00b7\u00b7"}}, {"rating": "5", "author": {"link": "https://www.douban.com/people/candyann/", "name": "\u871c\u4e1d\u5b89"}, "title": {"link": "https://movie.douban.com/review/1054914/", "name": "\u6de1\u6de1\u7684\u751f\u547d"}}, {"rating": "5", "author": {"link": "https://www.douban.com/people/66552525/", "name": "\u9178\u5976\u51b0\u6dc7\u6dcb"}, "title": {"link": "https://movie.douban.com/review/7754682/", "name": "\u7247\u9762\u7684\u89c6\u89d2"}}, {"rating": "4", "author": {"link": "https://www.douban.com/people/39072740/", "name": "\u6768\u5149\u5f20"}, "title": {"link": "https://movie.douban.com/review/6627653/", "name": "\u600e\u6837\u53cd\u6218"}}, {"rating": "5", "author": {"link": "https://www.douban.com/people/54443287/", "name": "\u98db\u9ce5\u904a\u9b5a"}, "title": {"link": "https://movie.douban.com/review/6323604/", "name": "\u76f8\u5173\u5f71\u8baf"}}, {"rating": "5", "author": {"link": "https://www.douban.com/people/chasy/", "name": "\u5c0f\u6298\u817e"}, "title": {"link": "https://movie.douban.com/review/5335099/", "name": "\u518d\u89c1\u8424\u706b\u866b"}}, {"rating": "4", "author": {"link": "https://www.douban.com/people/50343761/", "name": "\u753b\u672b"}, "title": {"link": "https://movie.douban.com/review/4977333/", "name": "\u4e0d\u80fd\u89e6\u78b0\u7b2c\u4e8c\u6b21\u7684\u201c\u8424\u706b\u866b\u4e4b\u5893\u201d"}}, {"rating": "4", "author": {"link": "https://www.douban.com/people/littlebasin/", "name": "\u5c0f\u76c6"}, "title": {"link": "https://movie.douban.com/review/4895859/", "name": "\u6ca1\u6709\u4eba\u662f\u65e0\u8f9c\u7684"}}, {"rating": "5", "author": {"link": "https://www.douban.com/people/50292654/", "name": "\u72fc\u5c45\u80e5"}, "title": {"link": "https://movie.douban.com/review/4872583/", "name": "\u866b\u513f\u98de"}}, {"rating": "5", "author": {"link": "https://www.douban.com/people/lovelygxj218/", "name": "juicy."}, "title": {"link": "https://movie.douban.com/review/4475055/", "name": "\u518d\u89c1\uff0c\u8424\u706b\u866b\u3002"}}, {"rating": "2", "author": {"link": "https://www.douban.com/people/subplant/", "name": "\u79d8\u5bc6\u5de5\u5382"}, "title": {"link": "https://movie.douban.com/review/3289828/", "name": "\u4e00\u8d2f\u4e0d\u77e5\u6240\u4e91\u7684\u9ad8\u7551\u52cb"}}, {"rating": "5", "author": {"link": "https://www.douban.com/people/kazia/", "name": "\u751c\u70e7\u767d"}, "title": {"link": "https://movie.douban.com/review/2955553/", "name": "\u5199\u7ed9\u8282\u5b50,\u8424\u706b\u866b\u7684\u56de\u5fc6,\u6211\u77e5\u9053\u6211\u4eec\u4f1a\u5728\u5929\u5802\u76f8\u9047"}}, {"rating": "5", "author": {"link": "https://www.douban.com/people/jerress/", "name": "\u5e03\u74dc"}, "title": {"link": "https://movie.douban.com/review/1103523/", "name": "\u751f\u547d\u7684\u5fae\u5149"}}, {"rating": "4", "author": {"link": "https://www.douban.com/people/sleepyray/", "name": "sleepyray"}, "title": {"link": "https://movie.douban.com/review/1020180/", "name": "\u6709\u4e00\u53e5\u8bdd\u8bf4\u5f97\u591a\u597d\u3002\u3002\u3002\u3002\u3002\u3002"}}, {"rating": "4", "author": {"link": "https://www.douban.com/people/1057541/", "name": "\u6e5b\u84dd"}, "title": {"link": "https://movie.douban.com/review/1013523/", "name": "\u5173\u4e8e\u5b69\u5b50"}}, {"rating": "1", "author": {"link": "https://www.douban.com/people/asuka/", "name": "\u9c7c\u4e38"}, "title": {"link": "https://movie.douban.com/review/1008631/", "name": "\u770b\u8fd9\u7247\u60f3\u5230\u7684\u6700\u591a\u7684\u4e00\u4e2a\u8bcd\u5c31\u662f:\u81ea\u4f5c\u81ea\u53d7"}}, {"rating": "4", "author": {"link": "https://www.douban.com/people/tass/", "name": "dizzyjon"}, "title": {"link": "https://movie.douban.com/review/1005293/", "name": "\u5386\u53f2\u4e0a\u6700\u538b\u6291\u7684\u52a8\u753b\u7247"}}, {"rating": "1", "author": {"link": "https://www.douban.com/people/141204065/", "name": "\u6a31\u6843\u4e2b\u5934"}, "title": {"link": "https://movie.douban.com/review/7752460/", "name": "\u8fd9\u4e24\u4e2a\u5b69\u5b50\u5f88\u53ef\u601c\uff1f"}}, {"rating": "4", "author": {"link": "https://www.douban.com/people/49888934/", "name": "\u9759\u8fdc"}, "title": {"link": "https://movie.douban.com/review/7559911/", "name": "\u50cf\u8424\u706b\u866b\u4e00\u6837\u7684\u751f\u547d"}}, {"rating": "2", "author": {"link": "https://www.douban.com/people/2652845/", "name": "\u54112\u8475"}, "title": {"link": "https://movie.douban.com/review/6406337/", "name": "\u4e0d\u660e\u767d\u4e3a\u4ec0\u4e48\u90a3\u4e48\u591a\u4eba\u4f1a\u559c\u6b22\u2026\u2026\u8fd8\u6cea\u5954\u2026\u2026"}}, {"rating": "1", "author": {"link": "https://www.douban.com/people/sailbarcelona/", "name": "\u6545\u91cc\u3002"}, "title": {"link": "https://movie.douban.com/review/6137918/", "name": "\u75db \u4e3a\u4ec0\u4e48\u4e0d\u575a\u5f3a"}}, {"rating": "2", "author": {"link": "https://www.douban.com/people/63187061/", "name": "Aya"}, "title": {"link": "https://movie.douban.com/review/5693051/", "name": "\u6b7b\u4ea1\u7684\u8fc7\u9519\u4e0d\u5728\u6218\u4e89\u800c\u662f\u81ea\u5df1"}}, {"rating": "4", "author": {"link": "https://www.douban.com/people/panwenjing/", "name": "\u73ab\u7470\u7981\u7159"}, "title": {"link": "https://movie.douban.com/review/5578905/", "name": "\u6d41\u6d6a\u513f\u6ca1\u6709\u6545\u4e61"}}, {"rating": "2", "author": {"link": "https://www.douban.com/people/53585412/", "name": "silver moon"}, "title": {"link": "https://movie.douban.com/review/5131398/", "name": "\u6218\u4e89\u4e4b\u751f\u5b58"}}, {"rating": "2", "author": {"link": "https://www.douban.com/people/47593447/", "name": "00s3r"}, "title": {"link": "https://movie.douban.com/review/5097636/", "name": "\u54c0\u5176\u4e0d\u5e78\uff0c\u6012\u5176\u4e0d\u4e89"}}, {"rating": "5", "author": {"link": "https://www.douban.com/people/4914300/", "name": "\u67ab\u6797\u6155\u96e8"}, "title": {"link": "https://movie.douban.com/review/5034378/", "name": "\u8424\u706b\u866b\u7684\u60b2\u4f24"}}, {"rating": "4", "author": {"link": "https://www.douban.com/people/42908934/", "name": "happy"}, "title": {"link": "https://movie.douban.com/review/5001517/", "name": "\u54e5\u54e5\u7684\u4e0d\u9760\u8c31\u5bb3\u6b7b\u4e86\u59b9\u59b9"}}, {"rating": "3", "author": {"link": "https://www.douban.com/people/40067511/", "name": "\u8fde\u57ce\u53c1\u6708"}, "title": {"link": "https://movie.douban.com/review/5001177/", "name": "\u8424\u706b\u866b\u4e4b\u5893\uff1a\u773c\u6cea\u906e\u4e0d\u4f4f\u5386\u53f2"}}, {"rating": "3", "author": {"link": "https://www.douban.com/people/51237415/", "name": "\u81ea\u7531\u7684\u5929\u7a7a"}, "title": {"link": "https://movie.douban.com/review/4976308/", "name": "\u5982\u679c\u6ca1\u6709\u66f4\u597d\u7684\u9009\u62e9\u8fd8\u662f\u7ef4\u6301\u539f\u72b6\u7684\u597d"}}, {"rating": "4", "author": {"link": "https://www.douban.com/people/gstone1723/", "name": "MUKI-J"}, "title": {"link": "https://movie.douban.com/review/3439849/", "name": "\u4e0d\u8981\u5014\u5f37--\u518d\u898b\u87a2\u706b\u87f2"}}, {"rating": "3", "author": {"link": "https://www.douban.com/people/3855764/", "name": "Vicky"}, "title": {"link": "https://movie.douban.com/review/3319050/", "name": "\u600e\u6837\u9009\u62e9"}}, {"rating": "3", "author": {"link": "https://www.douban.com/people/zhoujie84/", "name": "Gelate"}, "title": {"link": "https://movie.douban.com/review/3131717/", "name": "\u4f24\u611f\uff0c\u4f46\u6211\u4e0d\u80fd\u88ab\u5b8c\u5168\u611f\u52a8"}}, {"rating": "5", "author": {"link": "https://www.douban.com/people/15990318/", "name": "\u5c0f\u5c0f\u9e70"}, "title": {"link": "https://movie.douban.com/review/2898825/", "name": "\u8fd9\u6837\u7684\u6218\u4e89\u7247\u4e3a\u5565\u4e2d\u56fd\u4e0d\u62cd\uff1f"}}, {"rating": "5", "author": {"link": "https://www.douban.com/people/13332909/", "name": "bigman"}, "title": {"link": "https://movie.douban.com/review/2423325/", "name": "\u6218\u4e89\u91cc\u7684\u4eba\u6c11"}}, {"rating": "3", "author": {"link": "https://www.douban.com/people/1439418/", "name": "\u5927\u55b5\u545c"}, "title": {"link": "https://movie.douban.com/review/2244156/", "name": "\u633a\u8bbd\u523a\u7684"}}, {"rating": "5", "author": {"link": "https://www.douban.com/people/1413100/", "name": "\u6587\u68ee\u7279"}, "title": {"link": "https://movie.douban.com/review/2059549/", "name": "\u4e0d\u8bba\u4ec0\u4e48\u6218\u4e89\uff0c\u90fd\u662f\u6218\u4e89\u8d62\u4e86\uff01"}}, {"rating": "5", "author": {"link": "https://www.douban.com/people/3082520/", "name": "Michael"}, "title": {"link": "https://movie.douban.com/review/1532751/", "name": "\u6211\u5f88\u77db\u76fe"}}, {"rating": "5", "author": {"link": "https://www.douban.com/people/bladescepter/", "name": "\u54ab\u5c3a\u897f\u56ed"}, "title": {"link": "https://movie.douban.com/review/1357380/", "name": "\u9664\u4e86\u5403\u9971\uff0c\u6211\u4eec\u8fd8\u6709\u4ec0\u4e48\u9700\u8981\uff1f"}}, {"rating": "5", "author": {"link": "https://www.douban.com/people/shadowblue/", "name": "\u6c88\u5c0f\u6bdb\u4e0d\u8bf4\u8bdd"}, "title": {"link": "https://movie.douban.com/review/1324519/", "name": "\u8ba9\u6211\u4e3a\u4f60\u5531\u4e00\u652f\u5b89\u9b42\u66f2"}}, {"rating": "5", "author": {"link": "https://www.douban.com/people/xiaojia86/", "name": "\u9e2d\u9501\u9aa8"}, "title": {"link": "https://movie.douban.com/review/1123573/", "name": "\u7eaf\u771f\u4e4b\u6b7b"}}, {"rating": "5", "author": {"link": "https://www.douban.com/people/wyc0828/", "name": "\u5c0fWill"}, "title": {"link": "https://movie.douban.com/review/1046053/", "name": "\u518d\u89c1\uff0c\u8424\u706b\u866b"}}, {"rating": "4", "author": {"link": "https://www.douban.com/people/loger/", "name": "\u83e9\u63d0\u6811\u4e0b"}, "title": {"link": "https://movie.douban.com/review/1023260/", "name": "\u65e5\u672c\u4eba\u7684\u201c\u8f6f\u5b9e\u529b\u201d"}}, {"rating": "3", "author": {"link": "https://www.douban.com/people/gacktayu/", "name": "\u5e78\u8fd0\u5c0f\u5e06"}, "title": {"link": "https://movie.douban.com/review/7809494/", "name": "\u8424\u706b\u866b\u4e4b\u5893"}}, {"rating": "5", "author": {"link": "https://www.douban.com/people/34768836/", "name": "zaijieshan"}, "title": {"link": "https://movie.douban.com/review/7787707/", "name": "\u4e00\u5b9a\u4f1a\u54ed"}}, {"rating": "4", "author": {"link": "https://www.douban.com/people/53935985/", "name": "\u9c7c\u523a"}, "title": {"link": "https://movie.douban.com/review/7743592/", "name": "\u6218\u4e89\u4ece\u672a\u7ed3\u675f"}}, {"rating": "4", "author": {"link": "https://www.douban.com/people/72832633/", "name": "\u8fdf\u975e"}, "title": {"link": "https://movie.douban.com/review/7430538/", "name": "\u8bba\u600e\u4e48\u5e73\u5fc3\u9759\u6c14\u5730\u770b\u7535\u5f71"}}, {"rating": "3", "author": {"link": "https://www.douban.com/people/3369417/", "name": "\u521d\u9633"}, "title": {"link": "https://movie.douban.com/review/6860462/", "name": "\u795e\u4e0d\u80fd\u5230\u8fbe\u6bcf\u4e00\u4e2a\u5730\u65b9\uff0c\u4e8e\u662f\u4ed6\u521b\u9020\u4e86\u6bcd\u4eb2"}}, {"rating": "4", "author": {"link": "https://www.douban.com/people/clytze09/", "name": "\u7eff\u5c71\u5899\u7684\u5b89\u59ae"}, "title": {"link": "https://movie.douban.com/review/6359593/", "name": "\u518d\u89c1\u8424\u706b\u866b"}}, {"rating": "5", "author": {"link": "https://www.douban.com/people/axinlove/", "name": "axinlove"}, "title": {"link": "https://movie.douban.com/review/6152607/", "name": "\u300a\u706b\u5782\u308b\u306e\u5893[\u8424\u706b\u866b\u4e4b\u5893]\u300b\u7231\u603b\u662f\u8ba9\u4eba\u54ed"}}, {"rating": "3", "author": {"link": "https://www.douban.com/people/fuyun521/", "name": "\u6d6e\u4e91\u3002"}, "title": {"link": "https://movie.douban.com/review/5996139/", "name": "\u4ece\u5267\u4f5c\u6765\u8bc4\u6790"}}, {"rating": "1", "author": {"link": "https://www.douban.com/people/malasun7/", "name": "\u5b57\u98a0\u4e09\u53f7\u5012\u56db"}, "title": {"link": "https://movie.douban.com/review/5660942/", "name": "\u7f16\u5267\u624b\u6bb5\u592a\u4f4e\u52a3\u592a\u4e0b\u6d41"}}, {"rating": "4", "author": {"link": "https://www.douban.com/people/Jo--Jo/", "name": "\u4e5d\u5757\u94b1"}, "title": {"link": "https://movie.douban.com/review/5621573/", "name": "\u300a\u518d\u89c1\u8424\u706b\u866b\u300b \u611f\u52a8\u5728\u70b9\u6ef4\u4e4b\u95f4"}}, {"rating": "5", "author": {"link": "https://www.douban.com/people/14406200/", "name": "\u534a\u5c71\u516c\u56ed"}, "title": {"link": "https://movie.douban.com/review/4995156/", "name": "\u6c38\u8fdc\u7684\u8424\u706b\u866b\uff0c\u6c38\u8fdc\u4e0d\u5fd8\u7684\u5386\u53f2\u3002"}}, {"rating": "4", "author": {"link": "https://www.douban.com/people/1575216/", "name": "\u82cf\u5c0f\u9b1f"}, "title": {"link": "https://movie.douban.com/review/4937614/", "name": "\u5931\u8d25\u7684\u9ad8\u5e72\u5b50\u5f1f\u95f4\u63a5\u5bb3\u6b7b\u4e86\u81ea\u5df1\u59b9\u59b9\u7684\u6545\u4e8b"}}, {"rating": "5", "author": {"link": "https://www.douban.com/people/ccream/", "name": "\u4e0d\u518d"}, "title": {"link": "https://movie.douban.com/review/4581927/", "name": "\u53ea\u662f\u4e2a\u4eba\u611f\u53d7\u800c\u5df2"}}, {"rating": "5", "author": {"link": "https://www.douban.com/people/44073910/", "name": "\u6c5f\u5357\u6e14\u8005"}, "title": {"link": "https://movie.douban.com/review/3483902/", "name": "\u4e00\u90e8\u8ba9\u4e09\u5341\u5c81\u7537\u4eba\u59cb\u7ec8\u6d41\u6cea\u7684\u52a8\u753b\u7247\u2014\u2014\u6c38\u8fdc\u7684\u8bb0..."}}, {"rating": "4", "author": {"link": "https://www.douban.com/people/tintianten/", "name": "\u4eb2\u7231\u7684\uff1a\u6211\u4eec\u53ef\u4e0d\u80fd\u706d\u7edd\u2582\u2583\u2585\u2586"}, "title": {"link": "https://movie.douban.com/review/3382191/", "name": "\u50ac\u6cea\u7684\u7cd6\u679c\u76d2"}}, {"rating": "4", "author": {"link": "https://www.douban.com/people/aiyyo/", "name": "aiyyo"}, "title": {"link": "https://movie.douban.com/review/3308156/", "name": "\u8be5\u53cd\u601d\u7684\u90a3\u6bb5\u5386\u53f2"}}, {"rating": "3", "author": {"link": "https://www.douban.com/people/HangOnTheBox/", "name": "BluerElephant"}, "title": {"link": "https://movie.douban.com/review/2058393/", "name": "\u8282\u5b50\u662f\u88ab\u4ed6\u54e5\u54e5\u5bb3\u6b7b\u7684!"}}, {"rating": "4", "author": {"link": "https://www.douban.com/people/2658803/", "name": "Garfield"}, "title": {"link": "https://movie.douban.com/review/1959588/", "name": "\u6700\u597d\u7684\u53cd\u6218\u5f71\u7247"}}, {"rating": "5", "author": {"link": "https://www.douban.com/people/honey0520/", "name": "\u590f\u82e5\u6674.\u2764"}, "title": {"link": "https://movie.douban.com/review/1930100/", "name": "\u6211\u5df2\u7ecf\u5fd8\u4e86\u8be5\u5982\u4f55\u54ed\u6ce3"}}, {"rating": "5", "author": {"link": "https://www.douban.com/people/xumila/", "name": "\u8a31\u3002\u7c73\u62c9"}, "title": {"link": "https://movie.douban.com/review/1470248/", "name": "\u5185\u5fc3\u9178\u695a  \u65e0\u80fd\u4e3a\u529b"}}, {"rating": "4", "author": {"link": "https://www.douban.com/people/lanlanbetty/", "name": "\u6960"}, "title": {"link": "https://movie.douban.com/review/1383163/", "name": "\u60b2\u4f24\u7684\u60f3\u54ed"}}, {"rating": "4", "author": {"link": "https://www.douban.com/people/chocolatesnow/", "name": "\u8eca\u6b20\u7c73\u5510"}, "title": {"link": "https://movie.douban.com/review/1346282/", "name": "\u4e0d\u6562\u591a\u770b"}}, {"rating": "5", "author": {"link": "https://www.douban.com/people/lcliangying/", "name": "\u9896\u5b50\u7684\u5f71\u5b50"}, "title": {"link": "https://movie.douban.com/review/1211114/", "name": "\u5c0f\u5c0f\u7684\u611f\u52a8"}}, {"rating": "3", "author": {"link": "https://www.douban.com/people/dearkathy/", "name": "\u8212\u62c9"}, "title": {"link": "https://movie.douban.com/review/1058365/", "name": "\u9965\u997f\u4e0d\u987e\u53ca\u4efb\u4f55\u7f8e\u597d"}}, {"rating": "4", "author": {"link": "https://www.douban.com/people/gaze/", "name": "Samuel.D"}, "title": {"link": "https://movie.douban.com/review/1052353/", "name": "\u6d53\u91cd\u7684\u60b2\u54c0"}}, {"rating": "5", "author": {"link": "https://www.douban.com/people/1003168/", "name": "justine"}, "title": {"link": "https://movie.douban.com/review/1014256/", "name": "\u65e5\u672c,\u8ba9\u6211\u600e\u4e48\u770b\u5f85\u4f60"}}, {"rating": "4", "author": {"link": "https://www.douban.com/people/winterheath/", "name": "\u8354\u679d\u4e09\u5343"}, "title": {"link": "https://movie.douban.com/review/1005200/", "name": "\u65e0"}}, {"rating": "4", "author": {"link": "https://www.douban.com/people/ydpdwz/", "name": "ydpdwz"}, "title": {"link": "https://movie.douban.com/review/1002607/", "name": "\u90a3\u79cd\u65e0\u77e5\u7684\u5feb\u4e50"}}, {"rating": "4", "author": {"link": "https://www.douban.com/people/121627094/", "name": "\u6211\u6ca1\u54df"}, "title": {"link": "https://movie.douban.com/review/7987683/", "name": "\u8424\u706b\u866b\u4e4b\u5893"}}, {"rating": "4", "author": {"link": "https://www.douban.com/people/104545763/", "name": "\u5c0f\u4e91\u671b"}, "title": {"link": "https://movie.douban.com/review/7960764/", "name": "\u8424\u706b\u866b\u5149\u4e4b\u7184\u706d\u2014\u2014\u796d\u5960\u5144\u59b9\u90a3\u77ed\u6682\u7684\u751f\u547d"}}, {"rating": "3", "author": {"link": "https://www.douban.com/people/130324481/", "name": "\u5112\u58a8\u9053\u4e09\u5206"}, "title": {"link": "https://movie.douban.com/review/7689903/", "name": "\u300a\u8424\u706b\u866b\u4e4b\u5893\u300b\u4e0e\u53cd\u6218\u65e0\u5173"}}, {"rating": "4", "author": {"link": "https://www.douban.com/people/97187010/", "name": "huakaiyanran"}, "title": {"link": "https://movie.douban.com/review/7506844/", "name": "\u53ef\u601c\u4e4b\u4eba\u5fc5\u6709\u53ef\u6068\u4e4b\u5904~\u8424\u706b\u866b\u4e4b\u5893"}}, {"rating": "4", "author": {"link": "https://www.douban.com/people/73150320/", "name": "\u590d\u6d3b\u7684\u5b88\u591c\u4eba"}, "title": {"link": "https://movie.douban.com/review/7421283/", "name": "\u65e7\u8d26\u53f7\u65e7\u5f71\u8bc4\u642c\u8fd0\u4e4b\u672c\u5267\u77ed\u8bc4"}}, {"rating": "4", "author": {"link": "https://www.douban.com/people/83206457/", "name": "AmberIsland"}, "title": {"link": "https://movie.douban.com/review/7420564/", "name": "\u8fd8\u590d\u6742\u4e8e\u7b80\u5355"}}, {"rating": "4", "author": {"link": "https://www.douban.com/people/52872854/", "name": "\u77ed\u5c3e\u5df4\u7684\u5c0f\u9e1f"}, "title": {"link": "https://movie.douban.com/review/7384003/", "name": "100\u4e2a\u7ec6\u8282\u770b\u8424\u706b\u866b\u4e4b\u5893"}}, {"rating": "5", "author": {"link": "https://www.douban.com/people/AspireY/", "name": "\u5217\u8f66\u957f&solaris"}, "title": {"link": "https://movie.douban.com/review/7110132/", "name": "\u6ca1\u90a3\u4e48\u53f3\uff0c\u4e5f\u6ca1\u90a3\u4e48\u8bda"}}, {"rating": "3", "author": {"link": "https://www.douban.com/people/hzddsa/", "name": "\u6d69\u5b50\u591a\u8bfb\u4e66"}, "title": {"link": "https://movie.douban.com/review/6586866/", "name": "\u8424\u706b\u866b\u4e4b\u5893\uff0c7\u5206\u624d\u662f\u4e2a\u5408\u9002\u7684\u5206\u6570\u3002"}}, {"rating": "5", "author": {"link": "https://www.douban.com/people/13227290/", "name": "\u523b\u9aa8\u94ed\u5fc3"}, "title": {"link": "https://movie.douban.com/review/6555818/", "name": "\u5bf9\u300a\u8424\u706b\u866b\u4e4b\u5893\u300b\u90e8\u5206\u5267\u60c5\u7684\u7406\u89e3"}}, {"rating": "5", "author": {"link": "https://www.douban.com/people/ivy-in-ice/", "name": "ivy in ice"}, "title": {"link": "https://movie.douban.com/review/5965123/", "name": "\u5f53\u65f6\u6211\u5c31\u9707\u60ca\u4e86"}}, {"rating": "5", "author": {"link": "https://www.douban.com/people/70604120/", "name": "\u6728\u54c8\u54c8"}, "title": {"link": "https://movie.douban.com/review/5867217/", "name": "\u4e0d\u5fcd\u770b\u7b2c\u4e8c\u904d\u7684\u7535\u5f71"}}, {"rating": "5", "author": {"link": "https://www.douban.com/people/YangXueYFH/", "name": "\u5f20\u671b"}, "title": {"link": "https://movie.douban.com/review/5704948/", "name": "\u771f\u7684\u5730\u72f1"}}, {"rating": "4", "author": {"link": "https://www.douban.com/people/50525269/", "name": "\u738b\u5c0f\u51e1"}, "title": {"link": "https://movie.douban.com/review/5652178/", "name": "\u52a8\u753b\u505a\u5f97\u4e0d\u9519\uff0c\u6ca1\u5fc5\u8981\u4e71\u55b7\u7684"}}, {"rating": "4", "author": {"link": "https://www.douban.com/people/54858790/", "name": "\u624b\u62ff\u7834\u4ed1"}, "title": {"link": "https://movie.douban.com/review/5530366/", "name": "\u7ea2\u4e86\u773c\u7736\u7684\u8424\u706b\u866b"}}, {"rating": "5", "author": {"link": "https://www.douban.com/people/4540698/", "name": "\u6211\u4eec\u90fd\u662f\u5403\u8d27~"}, "title": {"link": "https://movie.douban.com/review/5529679/", "name": "\u6bcf\u4e00\u4e2a\u4eba\u90fd\u662f\u4e16\u754c\u72ec\u4e00\u65e0\u4e8c\u7684"}}, {"rating": "5", "author": {"link": "https://www.douban.com/people/59335165/", "name": "\u5343\u7199"}, "title": {"link": "https://movie.douban.com/review/5338792/", "name": "\u4e16\u754c\u548c\u5e73\u662f\u6211\u6700\u5927\u7684\u613f\u671b"}}, {"rating": "2", "author": {"link": "https://www.douban.com/people/4365580/", "name": "\u6625\u6625"}, "title": {"link": "https://movie.douban.com/review/5165742/", "name": "\u4e8c\u6218\uff0c\u4e0d\u662f\u53ea\u6709\u4e24\u9897\u539f\u5b50\u5f39"}}, {"rating": "5", "author": {"link": "https://www.douban.com/people/22461398/", "name": "\u6885\u5446\u5446"}, "title": {"link": "https://movie.douban.com/review/5082925/", "name": "\u6218\u4e89\u548c\u4eba\u6027"}}, {"rating": "5", "author": {"link": "https://www.douban.com/people/50735079/", "name": "\u4e00\u79cd\u5fc3\u60c5\u5728\u6577\u884d"}, "title": {"link": "https://movie.douban.com/review/4901078/", "name": "\u5f88\u597d\u770b"}}, {"rating": "5", "author": {"link": "https://www.douban.com/people/kissfingers/", "name": "kissfinger"}, "title": {"link": "https://movie.douban.com/review/4870783/", "name": "\u6e29\u60c5\u548c\u4eba\u6027"}}, {"rating": "4", "author": {"link": "https://www.douban.com/people/11965473/", "name": "\u8c01\u628a\u4f60\u5f53\u5b9d\u62a4\u7740"}, "title": {"link": "https://movie.douban.com/review/4447088/", "name": "\u53ea\u8981\u559c\u6b22\uff0c\u4e0d\u8981\u7231\u3002"}}, {"rating": "2", "author": {"link": "https://www.douban.com/people/43848526/", "name": "\u79d1\u9c7c"}, "title": {"link": "https://movie.douban.com/review/4028845/", "name": "\u8c01\u8bf4\u8fd9\u662f\u53cd\u6218\u7247\uff1f"}}, {"rating": "4", "author": {"link": "https://www.douban.com/people/44888280/", "name": "jcheers"}, "title": {"link": "https://movie.douban.com/review/3631952/", "name": "\u4e0d\u60f3\u518d\u770b\u7b2c\u4e8c\u904d\u7684\u5f71\u7247"}}, {"rating": "5", "author": {"link": "https://www.douban.com/people/43686753/", "name": "Bruce1990"}, "title": {"link": "https://movie.douban.com/review/3590932/", "name": "\u7a97\u5916\u98ce\u96e8\u96f7\u7535\uff0c\u5185\u5fc3\u5e73\u9759"}}, {"rating": "4", "author": {"link": "https://www.douban.com/people/42900161/", "name": "\u2620"}, "title": {"link": "https://movie.douban.com/review/3541533/", "name": "\u6211\u6ca1\u6389\u6cea\u3002"}}, {"rating": "5", "author": {"link": "https://www.douban.com/people/shangshishuo/", "name": "\u9b54\u74f6"}, "title": {"link": "https://movie.douban.com/review/3437432/", "name": "\u8bb8\u4e45\u6ca1\u6709\u7684\u611f\u52a8"}}, {"rating": "3", "author": {"link": "https://www.douban.com/people/34513010/", "name": "alexwillows"}, "title": {"link": "https://movie.douban.com/review/3429937/", "name": "\u4fb5\u7565\u8005\uff0c\u662f\u5e94\u8be5\u8981\u53cd\u7701\u4e00\u4e0b\u81ea\u5df1\u7684"}}, {"rating": "5", "author": {"link": "https://www.douban.com/people/40328283/", "name": "\u5929\u4f7f\u7231\u88ab\u7a9d"}, "title": {"link": "https://movie.douban.com/review/3390439/", "name": "\u6218\u4e89\u7247\u770b\u5230\u6700\u540e"}}, {"rating": "5", "author": {"link": "https://www.douban.com/people/peach.M.yj.W/", "name": "[\u5df2\u6ce8\u9500]"}, "title": {"link": "https://movie.douban.com/review/3131173/", "name": "\u505c\u4e0b\u4e86\u5f88\u591a\u6b21"}}, {"rating": "5", "author": {"link": "https://www.douban.com/people/break-Trance/", "name": "\u963f\u5e03"}, "title": {"link": "https://movie.douban.com/review/2935444/", "name": "\u8bf7\u90a3\u4e9bTAG\u4e3a\u5bab\u5d0e\u9a8f\u7684\u4eba\uff0c\u64e6\u4eae\u4f60\u7684\u773c\u775b\u3002"}}, {"rating": "5", "author": {"link": "https://www.douban.com/people/helizhanglao/", "name": "\u6cb3\u72f8"}, "title": {"link": "https://movie.douban.com/review/2830188/", "name": "\u5df1\u6240\u4e0d\u6b32\uff0c\u52ff\u65bd\u4e8e\u4eba\u3002"}}, {"rating": "5", "author": {"link": "https://www.douban.com/people/woaikanlongmao/", "name": "Tristan"}, "title": {"link": "https://movie.douban.com/review/2803143/", "name": "\u518d\u89c1\u8424\u706b\u866b"}}, {"rating": "4", "author": {"link": "https://www.douban.com/people/anice/", "name": "\u82bd \u8863*"}, "title": {"link": "https://movie.douban.com/review/2535364/", "name": "\u6211\u4eec\u90fd\u662f\u90a3\u6e3a\u5c0f\u5351\u5fae\u7684\u4e00\u4e2a\u3002"}}, {"rating": "5", "author": {"link": "https://www.douban.com/people/5910696/", "name": "\u51dd\u67ab\u98de"}, "title": {"link": "https://movie.douban.com/review/2343169/", "name": "\u90a3\u4e00\u7f50\u7cd6\u6c34"}}, {"rating": "4", "author": {"link": "https://www.douban.com/people/overlydaunting/", "name": "\u94c1\u68cd\u7537\u5b69\u51af\u626f\u626f"}, "title": {"link": "https://movie.douban.com/review/2296741/", "name": "\u5c0f\u65f6\u5019\uff0c\u7b2c\u4e00\u624b\u7684\u559c\u6b22"}}, {"rating": "5", "author": {"link": "https://www.douban.com/people/6888002/", "name": "\u87f9\u87f9"}, "title": {"link": "https://movie.douban.com/review/2252728/", "name": "\u8424\u706b\u866b\u4e4b\u5893"}}, {"rating": "5", "author": {"link": "https://www.douban.com/people/loveyoung130412/", "name": "Sylvia"}, "title": {"link": "https://movie.douban.com/review/2163436/", "name": "\u4e0a\u5e1d\u6536\u8d70\u5584\u826f\u7684\u70df\uff0c\u7559\u4e0b\u7f6a\u6076\u7684\u5c18\u3002"}}, {"rating": "4", "author": {"link": "https://www.douban.com/people/4245563/", "name": "[\u5df2\u6ce8\u9500]"}, "title": {"link": "https://movie.douban.com/review/2137142/", "name": "\u6210\u4e3a\u4f60\u81ea\u5df1"}}, {"rating": "4", "author": {"link": "https://www.douban.com/people/sssssai/", "name": "FFFFFJM"}, "title": {"link": "https://movie.douban.com/review/1934817/", "name": "\u518d\u89c1\uff0c\u518d\u89c1\u3002"}}, {"rating": "3", "author": {"link": "https://www.douban.com/people/3234409/", "name": "\u827e\u6843\u6cfd"}, "title": {"link": "https://movie.douban.com/review/1616296/", "name": "\u201c\u5e94\u8be5\u201d\u611f\u52a8\u3001\u5b66\u4f1a\u611f\u52a8\u3001\u611f\u52a8\u800c\u7231\u00b7\u6218\u4e89\u5c31\u662f\u707e\u96be"}}, {"rating": "4", "author": {"link": "https://www.douban.com/people/fallrain888/", "name": "fallrain369"}, "title": {"link": "https://movie.douban.com/review/1592164/", "name": "\u4e00\u4e9b\u60f3\u6cd5"}}, {"rating": "5", "author": {"link": "https://www.douban.com/people/2588629/", "name": "\u7eaa\u826f\u751f"}, "title": {"link": "https://movie.douban.com/review/1551725/", "name": "\u8424\u706b\u866b\uff0c\u539f\u6765\u4e5f\u53ef\u4ee5\u662f\u4ee3\u8868\u5e0c\u671b"}}, {"rating": "5", "author": {"link": "https://www.douban.com/people/jenny528/", "name": "Clea Ma"}, "title": {"link": "https://movie.douban.com/review/1506943/", "name": "\u552f\u4e00"}}, {"rating": "5", "author": {"link": "https://www.douban.com/people/ancheng/", "name": "\u5b89\u57ce"}, "title": {"link": "https://movie.douban.com/review/1407826/", "name": "\u9019\u500b\u4e16\u754c\u5e76\u4e0d\u662f\u55ae\u7d14\u7684\u7c21\u55ae"}}, {"rating": "5", "author": {"link": "https://www.douban.com/people/PIGSKY/", "name": "\u60f3\u50cf\u732a\u4e00\u6837\u7684\u98de"}, "title": {"link": "https://movie.douban.com/review/1368157/", "name": "\u5f88\u5f3a\u5927.\u5f88\u597d."}}, {"rating": "3", "author": {"link": "https://www.douban.com/people/realf/", "name": "\u60e0\u660e"}, "title": {"link": "https://movie.douban.com/review/1365003/", "name": "\u8367\u5149\u70b9\u70b9...\u800c\u5df2"}}, {"rating": "4", "author": {"link": "https://www.douban.com/people/yimee/", "name": "\u7c73\u4e00"}, "title": {"link": "https://movie.douban.com/review/1360837/", "name": "\u6a21\u7cca\u4e86\u89c6\u7ebf"}}, {"rating": "5", "author": {"link": "https://www.douban.com/people/lovesnow/", "name": "\u590f\u98ce"}, "title": {"link": "https://movie.douban.com/review/1358831/", "name": "\u706b\u5782\u308b\u306e\u5893\uff0d\u611f\u52a8"}}, {"rating": "5", "author": {"link": "https://www.douban.com/people/i_can/", "name": "\u5708\u5708"}, "title": {"link": "https://movie.douban.com/review/1299550/", "name": "\u4e0d\u8be5\u8fd9\u65f6\u5019\u770b\u7684......"}}, {"rating": "5", "author": {"link": "https://www.douban.com/people/1808542/", "name": "Sylvia"}, "title": {"link": "https://movie.douban.com/review/1273547/", "name": "\u732e\u7ed9\u201c\u518d\u89c1\u8424\u706b\u866b\u201d"}}, {"rating": "5", "author": {"link": "https://www.douban.com/people/1467160/", "name": "setshooter"}, "title": {"link": "https://movie.douban.com/review/1248496/", "name": "\u8fd8\u662f\u6ca1\u6709\u540d\u5b57\u5427~"}}, {"rating": "5", "author": {"link": "https://www.douban.com/people/FreeGhost/", "name": ".\u6d6e\u783e\u6208\u65af\u5854"}, "title": {"link": "https://movie.douban.com/review/1212236/", "name": "\u518d\u89c1"}}, {"rating": "2", "author": {"link": "https://www.douban.com/people/1315431/", "name": "\u660e\u6708\u5fc3"}, "title": {"link": "https://movie.douban.com/review/1173350/", "name": "\u4e0d\u77e5\u9053\u5728\u65e5\u672c\u4fb5\u534e\u671f\u95f4\u6709\u591a\u5c11\u4e2d\u56fd\u7684\u5b69\u5b50\u50cf\u4ed6\u4eec\u5144..."}}, {"rating": "4", "author": {"link": "https://www.douban.com/people/hebinmin/", "name": "\u8def\u4eba\u997c"}, "title": {"link": "https://movie.douban.com/review/1172932/", "name": "\u6218\u4e89\u7247\u7684\u5173\u6ce8\u70b9"}}, {"rating": "5", "author": {"link": "https://www.douban.com/people/1635161/", "name": "infinity\u5927\u53ef"}, "title": {"link": "https://movie.douban.com/review/1171870/", "name": "\u4e00\u90e8\u4ee4\u6211\u5fc3\u52a8\u7684\u52a8\u753b\u7247\uff01\uff01"}}, {"rating": "5", "author": {"link": "https://www.douban.com/people/Bambus/", "name": "Bambus"}, "title": {"link": "https://movie.douban.com/review/1124609/", "name": "\u518d\u89c1\u5427\u8424\u706b\u866b"}}, {"rating": "4", "author": {"link": "https://www.douban.com/people/windtunle/", "name": "\u4e03\u5915\u96e8\u4eba"}, "title": {"link": "https://movie.douban.com/review/1120813/", "name": "\u4e0d\u8bf4\u518d\u89c1"}}, {"rating": "5", "author": {"link": "https://www.douban.com/people/1194808/", "name": "\u5c0f\u867e\u7096\u996d"}, "title": {"link": "https://movie.douban.com/review/1100873/", "name": "\u6b8b\u9177"}}, {"rating": "3", "author": {"link": "https://www.douban.com/people/1163839/", "name": "\u4e8c\u519c\u620f\u732a"}, "title": {"link": "https://movie.douban.com/review/1066727/", "name": "\u6211\u770b\u8fd9\u90e8\u7535\u5f71"}}, {"rating": "5", "author": {"link": "https://www.douban.com/people/wishdan/", "name": "\u4e86\u4e86\u4e0d\u4e86"}, "title": {"link": "https://movie.douban.com/review/1064904/", "name": "\u518d\u89c1\u8424\u706b\u866b"}}, {"rating": "5", "author": {"link": "https://www.douban.com/people/zhangyi8849/", "name": "[\u5df2\u6ce8\u9500]"}, "title": {"link": "https://movie.douban.com/review/1052992/", "name": "\u8424\u706b\u866b\u7684\u5149\u8292"}}, {"rating": "3", "author": {"link": "https://www.douban.com/people/halleybachelor/", "name": "halleybachelor"}, "title": {"link": "https://movie.douban.com/review/1034956/", "name": "\u8424\u706b\u866b\u4e4b\u5893"}}, {"rating": "4", "author": {"link": "https://www.douban.com/people/app/", "name": "[\u5df2\u6ce8\u9500]"}, "title": {"link": "https://movie.douban.com/review/1020249/", "name": "\u6218\u4e89\u5f88\u6b8b\u9177\u554a"}}, {"rating": "4", "author": {"link": "https://www.douban.com/people/mayjoy2000/", "name": "\u84dd\u6615\u7f8e"}, "title": {"link": "https://movie.douban.com/review/1010119/", "name": "\u7cd6\uff0d\uff0d\u518d\u89c1\u8424\u706b\u866b"}}, {"rating": "5", "author": {"link": "https://www.douban.com/people/133533044/", "name": "\u80a5\u561f\u561f\u5de6\u536b\u95e8"}, "title": {"link": "https://movie.douban.com/review/8083146/", "name": "\u81f4\u6240\u6709\u8bc41\u5206\u7684\u4eba"}}, {"rating": "4", "author": {"link": "https://www.douban.com/people/96934508/", "name": "\u98ce\u8fc7\u8083\u6740"}, "title": {"link": "https://movie.douban.com/review/8048359/", "name": "\u77ed\u8bc4\u5199\u4e0d\u4e0b\u4e86\u957f\u8bc4\u6491"}}, {"rating": "2", "author": {"link": "https://www.douban.com/people/soldar/", "name": "\u54f2\u522b"}, "title": {"link": "https://movie.douban.com/review/8007125/", "name": "\u5bfc\u6f14\u8fd9\u6837\u201c\u53cd\u601d\u201d\u6218\u4e89\uff1f"}}, {"rating": "5", "author": {"link": "https://www.douban.com/people/139450370/", "name": "DEEP"}, "title": {"link": "https://movie.douban.com/review/8006621/", "name": "\u4ed6\u4eec\u6bd5\u7adf\u8fd8\u90fd\u662f\u5b69\u5b50"}}, {"rating": "3", "author": {"link": "https://www.douban.com/people/139910044/", "name": "Eileen"}, "title": {"link": "https://movie.douban.com/review/7918499/", "name": "\u8fd9\u771f\u7684\u662f\u4e00\u90e8\u53cd\u6218\u7535\u5f71\u5417\uff1f"}}, {"rating": "5", "author": {"link": "https://www.douban.com/people/71255953/", "name": "\u4e00\u9a91\u7ea2\u5c18\u5983\u5b50\u7b11"}, "title": {"link": "https://movie.douban.com/review/7837007/", "name": "\u5929\u5802\u6ca1\u6709\u5fe7\u4f24"}}, {"rating": "3", "author": {"link": "https://www.douban.com/people/tyfoy/", "name": "\u5b87\u796d"}, "title": {"link": "https://movie.douban.com/review/7815483/", "name": "\u672c\u6765\u662f\u60f3\u53d1\u77ed\u8bc4\u7684"}}, {"rating": "4", "author": {"link": "https://www.douban.com/people/46903433/", "name": "\u6c89\u6d6a"}, "title": {"link": "https://movie.douban.com/review/7788389/", "name": "\u6218\u4e89\u603b\u662f\u6b8b\u9177\u7684"}}, {"rating": "5", "author": {"link": "https://www.douban.com/people/4624797/", "name": "\u6cd5\u9e23"}, "title": {"link": "https://movie.douban.com/review/7686079/", "name": "\u6108\u662f\u7f8e\u7684\u610f\u5411\uff0c\u6108\u662f\u53cd\u886c\u6218\u4e89\u7684\u6b8b\u9177"}}, {"rating": "5", "author": {"link": "https://www.douban.com/people/57970271/", "name": "1Continent"}, "title": {"link": "https://movie.douban.com/review/7680634/", "name": "\u7535\u5f71\u53ea\u662f\u5199\u5b9e\u5730\u8bb2\u8ff0\u4e00\u4e2a\u60b2\u5267"}}, {"rating": "5", "author": {"link": "https://www.douban.com/people/132523716/", "name": "\u62c9\u98ce\u7684\u8003\u62c9"}, "title": {"link": "https://movie.douban.com/review/7673284/", "name": "\u540e20\u5206\u949f\u54ed\u6210\u72d7\uff01"}}], "related_info": "\n                                \u3000\u3000\u7f8e\u65e5\u6218\u4e89\u7206\u53d1\uff0c14\u5c81\u7684\u6e05\u592a\u5e26\u7740\u5e74\u5e7c\u7684\u59b9\u59b9\u5230\u5904\u9003\u547d\uff0c\u5f53\u4ed6\u4eec\u5230\u8fbe\u9632\u7a7a\u6d1e\u7684\u65f6\u5019\uff0c\u6bcd\u4eb2\u5df2\u8eab\u53d7\u91cd\u4f24\uff0c\u6ca1\u8fc7\u591a\u4e45\u4fbf\u4e0d\u4e45\u4eba\u4e16\u3002\u4e24\u5144\u59b9\u81ea\u6b64\u8fc7\u7740\u76f8\u4f9d\u4e3a\u547d\u7684\u65e5\u5b50\u3002\u4ed6\u4eec\u53ea\u597d\u6295\u9760\u4e86\u6bcd\u4eb2\u7684\u59d0\u59b9\uff0c\u7eb5\u4f7f\u4ed6\u4eec\u628a\u5bb6\u91cc\u6240\u6709\u7684\u5bb6\u5f53\u90fd\u9001\u7ed9\u4e86\u963f\u59e8\uff0c\u4f46\u5f53\u98df\u7269\u5403\u5b8c\uff0c\u4ed6\u4eec\u5c31\u8d8a\u611f\u5230\u4e86\u5bc4\u4eba\u7bf1\u4e0b\u7684\u611f\u89c9\uff0c\u6e05\u592a\u51b3\u5b9a\u5e26\u7740\u59b9\u59b9\u79bb\u5f00\u72ec\u81ea\u751f\u6d3b\u3002\u706b\u707e\u785d\u70df\u4e2d\u7684\u751f\u6d3b\u5e76\u4e0d\u597d\u8fc7\uff0c\u6e05\u592a\u4e3a\u4e86\u59b9\u59b9\u56db\u5904\u5077\u53d6\u98df\u7269\uff0c\u4f46\u59b9\u59b9\u8fd8\u662f\u4e25\u91cd\u8425\u517b\u4e0d\u826f\u2026\u2026\n                        ", "award": [], "related_movie": [{"url": "https://movie.douban.com/subject/1297359/", "name": "\n\u5e7d\u7075\u516c\u4e3b\n"}, {"url": "https://movie.douban.com/subject/1291585/", "name": "\n\u98ce\u4e4b\u8c37\n"}, {"url": "https://movie.douban.com/subject/1291583/", "name": "\n\u5929\u7a7a\u4e4b\u57ce\n"}, {"url": "https://movie.douban.com/subject/1307811/", "name": "\n\u9b54\u5973\u5b85\u6025\u4fbf\n"}, {"url": "https://movie.douban.com/subject/1308807/", "name": "\n\u54c8\u5c14\u7684\u79fb\u52a8\u57ce\u5821\n"}, {"url": "https://movie.douban.com/subject/1959877/", "name": "\n\u60ac\u5d16\u4e0a\u7684\u91d1\u9c7c\u59ec\n"}, {"url": "https://movie.douban.com/subject/1304970/", "name": "\n\u732b\u7684\u62a5\u6069\n"}, {"url": "https://movie.douban.com/subject/1297052/", "name": "\n\u4fa7\u8033\u503e\u542c\n"}, {"url": "https://movie.douban.com/subject/1303907/", "name": "\n\u767e\u53d8\u72f8\u732b\n"}, {"url": "https://movie.douban.com/subject/1291838/", "name": "\n\u7ea2\u732a\n"}], "interest": {"rate": "8.7", "rating_people_num": "177900", "rating_per": ["52.9%", "33.7%", "11.1%", "1.4%", "0.9%"], "rating_better": ["91% \u52a8\u753b\u7247", "93% \u6218\u4e89\u7247"]}, "year": "(1988)", "movie_url": "https://movie.douban.com/subject/1293318/"}