{"comment": [{"rating": "5", "vote_num": "928", "author": {"link": "https://www.douban.com/people/forestdc/", "name": "\u5e7b\u89c9\uff0c\u90fd\u662f\u5e7b\u89c9"}}, {"rating": "5", "vote_num": "237", "author": {"link": "https://www.douban.com/people/Soniawoolf/", "name": "[\u5df2\u6ce8\u9500]"}}, {"rating": "4", "vote_num": "189", "author": {"link": "https://www.douban.com/people/ocean_kwai/", "name": "\u6218\u56fd\u5ba2"}}, {"rating": "5", "vote_num": "144", "author": {"link": "https://www.douban.com/people/cuican/", "name": "\u7480\u74a8"}}, {"rating": "5", "vote_num": "121", "author": {"link": "https://www.douban.com/people/zishuiyilan/", "name": "\u8587\u7f85\u5c3c\u5361"}}, {"rating": "4", "vote_num": "82", "author": {"link": "https://www.douban.com/people/inlighthouse/", "name": "Icy"}}, {"rating": "5", "vote_num": "87", "author": {"link": "https://www.douban.com/people/Over5/", "name": "Over5"}}, {"rating": "5", "vote_num": "89", "author": {"link": "https://www.douban.com/people/VivienAlbarn/", "name": "[\u5df2\u6ce8\u9500]"}}, {"rating": "3", "vote_num": "66", "author": {"link": "https://www.douban.com/people/jimo/", "name": "\u8001\u9e21\uff5c\u6276\u7acb"}}, {"rating": "3", "vote_num": "60", "author": {"link": "https://www.douban.com/people/clownyours/", "name": "Lesley10"}}, {"rating": "5", "vote_num": "50", "author": {"link": "https://www.douban.com/people/2129544/", "name": "\u82cf\u683c\u5170\u683c"}}, {"rating": "3", "vote_num": "30", "author": {"link": "https://www.douban.com/people/luc1en/", "name": "luc1en"}}, {"rating": "5", "vote_num": "14", "author": {"link": "https://www.douban.com/people/hideinthecrowd/", "name": "[\u5df2\u6ce8\u9500]"}}, {"rating": "5", "vote_num": "0", "author": {"link": "https://www.douban.com/people/jackslsmm/", "name": "\u7eb3\u4ec0\u7ef4\u5c14\u7684\u732b"}}, {"rating": "5", "vote_num": "0", "author": {"link": "https://www.douban.com/people/54032152/", "name": "\u96f6\u7396\u8d30\u8d30"}}, {"rating": "4", "vote_num": "0", "author": {"link": "https://www.douban.com/people/60619534/", "name": "Another"}}, {"rating": "4", "vote_num": "0", "author": {"link": "https://www.douban.com/people/1458865/", "name": "\u02c7\u00b7\u02c9Gaara"}}, {"rating": "4", "vote_num": "0", "author": {"link": "https://www.douban.com/people/64422636/", "name": "Yuki"}}, {"rating": "4", "vote_num": "0", "author": {"link": "https://www.douban.com/people/45531734/", "name": "\u9762\u5305\u4e0d\u5939\u5fc3"}}, {"rating": "4", "vote_num": "0", "author": {"link": "https://www.douban.com/people/windrainride/", "name": "\u98ce\u96e8\u9a91\u8001\u5e08"}}, {"rating": "3", "vote_num": "1", "author": {"link": "https://www.douban.com/people/veverlee/", "name": "\u5185\u9646\u98de\u9c7c"}}, {"rating": "4", "vote_num": "0", "author": {"link": "https://www.douban.com/people/wangmei/", "name": "\u915a\u915e"}}, {"rating": "5", "vote_num": "0", "author": {"link": "https://www.douban.com/people/yaogunxuanzang/", "name": "\u6447\u6eda\u7384\u5958"}}, {"rating": "5", "vote_num": "0", "author": {"link": "https://www.douban.com/people/dorothyzhang/", "name": "\u9972\u517b\u5e7b\u60f3"}}, {"rating": "3", "vote_num": "0", "author": {"link": "https://www.douban.com/people/kick-my-ass/", "name": "\u9ad8\u538b\u7535"}}, {"rating": "4", "vote_num": "0", "author": {"link": "https://www.douban.com/people/48099521/", "name": "\u5e78\u8fd0\u5362\u514b"}}, {"rating": "4", "vote_num": "0", "author": {"link": "https://www.douban.com/people/albertina/", "name": "AL"}}, {"rating": "2", "vote_num": "0", "author": {"link": "https://www.douban.com/people/gtan/", "name": "\u914b\u957f"}}, {"rating": "5", "vote_num": "0", "author": {"link": "https://www.douban.com/people/31878818/", "name": "\u9752\u9edb"}}, {"rating": "4", "vote_num": "0", "author": {"link": "https://www.douban.com/people/zhaopeng007/", "name": "\u8d75\u9e4f"}}, {"rating": "3", "vote_num": "0", "author": {"link": "https://www.douban.com/people/yrh/", "name": "yrh"}}, {"rating": "5", "vote_num": "0", "author": {"link": "https://www.douban.com/people/mrg/", "name": "G||\u5927\u8089\u9ebb"}}, {"rating": "4", "vote_num": "0", "author": {"link": "https://www.douban.com/people/landelanle/", "name": "\u61d2\u5f97\u61d2\u4e86"}}, {"rating": "3", "vote_num": "0", "author": {"link": "https://www.douban.com/people/56800653/", "name": "@large"}}, {"rating": "4", "vote_num": "0", "author": {"link": "https://www.douban.com/people/windrainride/", "name": "\u98ce\u96e8\u9a91\u8001\u5e08"}}, {"rating": "3", "vote_num": "1", "author": {"link": "https://www.douban.com/people/veverlee/", "name": "\u5185\u9646\u98de\u9c7c"}}, {"rating": "4", "vote_num": "0", "author": {"link": "https://www.douban.com/people/wangmei/", "name": "\u915a\u915e"}}, {"rating": "5", "vote_num": "0", "author": {"link": "https://www.douban.com/people/yaogunxuanzang/", "name": "\u6447\u6eda\u7384\u5958"}}, {"rating": "5", "vote_num": "0", "author": {"link": "https://www.douban.com/people/dorothyzhang/", "name": "\u9972\u517b\u5e7b\u60f3"}}, {"rating": "3", "vote_num": "0", "author": {"link": "https://www.douban.com/people/kick-my-ass/", "name": "\u9ad8\u538b\u7535"}}, {"rating": "4", "vote_num": "0", "author": {"link": "https://www.douban.com/people/48099521/", "name": "\u5e78\u8fd0\u5362\u514b"}}, {"rating": "4", "vote_num": "0", "author": {"link": "https://www.douban.com/people/albertina/", "name": "AL"}}, {"rating": "2", "vote_num": "0", "author": {"link": "https://www.douban.com/people/gtan/", "name": "\u914b\u957f"}}, {"rating": "5", "vote_num": "0", "author": {"link": "https://www.douban.com/people/31878818/", "name": "\u9752\u9edb"}}, {"rating": "4", "vote_num": "0", "author": {"link": "https://www.douban.com/people/zhaopeng007/", "name": "\u8d75\u9e4f"}}, {"rating": "3", "vote_num": "0", "author": {"link": "https://www.douban.com/people/yrh/", "name": "yrh"}}, {"rating": "5", "vote_num": "0", "author": {"link": "https://www.douban.com/people/mrg/", "name": "G||\u5927\u8089\u9ebb"}}, {"rating": "4", "vote_num": "0", "author": {"link": "https://www.douban.com/people/landelanle/", "name": "\u61d2\u5f97\u61d2\u4e86"}}, {"rating": "3", "vote_num": "0", "author": {"link": "https://www.douban.com/people/56800653/", "name": "@large"}}, {"rating": "5", "vote_num": "0", "author": {"link": "https://www.douban.com/people/blueboy2212/", "name": "\u84dd\u4eba"}}, {"rating": "5", "vote_num": "0", "author": {"link": "https://www.douban.com/people/betterthanrenee/", "name": "Renee"}}, {"rating": "4", "vote_num": "0", "author": {"link": "https://www.douban.com/people/3403686/", "name": "\u8d85cute\u4fa0"}}, {"rating": "3", "vote_num": "0", "author": {"link": "https://www.douban.com/people/pingfandeshabi/", "name": "\u5b66\u54273.0"}}, {"rating": "4", "vote_num": "0", "author": {"link": "https://www.douban.com/people/puhuahua/", "name": "\u5f71\u9752\u5eb8"}}, {"rating": "4", "vote_num": "0", "author": {"link": "https://www.douban.com/people/landelanle/", "name": "\u61d2\u5f97\u61d2\u4e86"}}, {"rating": "3", "vote_num": "0", "author": {"link": "https://www.douban.com/people/56800653/", "name": "@large"}}, {"rating": "5", "vote_num": "0", "author": {"link": "https://www.douban.com/people/blueboy2212/", "name": "\u84dd\u4eba"}}, {"rating": "5", "vote_num": "0", "author": {"link": "https://www.douban.com/people/betterthanrenee/", "name": "Renee"}}, {"rating": "4", "vote_num": "0", "author": {"link": "https://www.douban.com/people/3403686/", "name": "\u8d85cute\u4fa0"}}, {"rating": "3", "vote_num": "0", "author": {"link": "https://www.douban.com/people/pingfandeshabi/", "name": "\u5b66\u54273.0"}}, {"rating": "4", "vote_num": "0", "author": {"link": "https://www.douban.com/people/puhuahua/", "name": "\u5f71\u9752\u5eb8"}}, {"rating": "5", "vote_num": "0", "author": {"link": "https://www.douban.com/people/onlysha/", "name": "s"}}, {"rating": "4", "vote_num": "0", "author": {"link": "https://www.douban.com/people/blackeleven/", "name": "\u82cf\u82cf"}}, {"rating": "4", "vote_num": "0", "author": {"link": "https://www.douban.com/people/40235686/", "name": "eight"}}, {"rating": "5", "vote_num": "0", "author": {"link": "https://www.douban.com/people/bfu/", "name": "tofubo"}}, {"rating": "5", "vote_num": "0", "author": {"link": "https://www.douban.com/people/dbhungry/", "name": "hungry"}}, {"rating": "4", "vote_num": "0", "author": {"link": "https://www.douban.com/people/shine905/", "name": "\u5361\u5361\u6d1b\u7279"}}, {"rating": "4", "vote_num": "0", "author": {"link": "https://www.douban.com/people/seanhay/", "name": "\u772f\u772f\u773c\u4e60\u4e60"}}, {"rating": "5", "vote_num": "0", "author": {"link": "https://www.douban.com/people/qsb1985/", "name": "\u7ef4\u7ef4"}}, {"rating": "5", "vote_num": "0", "author": {"link": "https://www.douban.com/people/snowman1209/", "name": "\u84fc\u84dd"}}, {"rating": "4", "vote_num": "0", "author": {"link": "https://www.douban.com/people/43653775/", "name": "\u53f6\u679c\u9c81\u4ec0\u5361"}}, {"rating": "4", "vote_num": "0", "author": {"link": "https://www.douban.com/people/54653121/", "name": "\u738b\u5c0f\u82b1"}}, {"rating": "5", "vote_num": "0", "author": {"link": "https://www.douban.com/people/12678743/", "name": "\u4e00\u7136\u7684\u6d77\u5c9b"}}, {"rating": "5", "vote_num": "0", "author": {"link": "https://www.douban.com/people/weilaipsalms/", "name": "\u5f20\u672a\u6765"}}, {"rating": "5", "vote_num": "0", "author": {"link": "https://www.douban.com/people/bfu/", "name": "tofubo"}}, {"rating": "5", "vote_num": "0", "author": {"link": "https://www.douban.com/people/dbhungry/", "name": "hungry"}}, {"rating": "4", "vote_num": "0", "author": {"link": "https://www.douban.com/people/shine905/", "name": "\u5361\u5361\u6d1b\u7279"}}, {"rating": "4", "vote_num": "0", "author": {"link": "https://www.douban.com/people/seanhay/", "name": "\u772f\u772f\u773c\u4e60\u4e60"}}, {"rating": "5", "vote_num": "0", "author": {"link": "https://www.douban.com/people/qsb1985/", "name": "\u7ef4\u7ef4"}}, {"rating": "5", "vote_num": "0", "author": {"link": "https://www.douban.com/people/snowman1209/", "name": "\u84fc\u84dd"}}, {"rating": "4", "vote_num": "0", "author": {"link": "https://www.douban.com/people/43653775/", "name": "\u53f6\u679c\u9c81\u4ec0\u5361"}}, {"rating": "4", "vote_num": "0", "author": {"link": "https://www.douban.com/people/54653121/", "name": "\u738b\u5c0f\u82b1"}}, {"rating": "5", "vote_num": "0", "author": {"link": "https://www.douban.com/people/12678743/", "name": "\u4e00\u7136\u7684\u6d77\u5c9b"}}, {"rating": "5", "vote_num": "0", "author": {"link": "https://www.douban.com/people/weilaipsalms/", "name": "\u5f20\u672a\u6765"}}, {"rating": "5", "vote_num": "0", "author": {"link": "https://www.douban.com/people/donchen/", "name": "\u68a6\u6cfd\u4ed6\u7238"}}, {"rating": "4", "vote_num": "0", "author": {"link": "https://www.douban.com/people/zOedOng/", "name": "Zoedong_"}}, {"rating": "4", "vote_num": "0", "author": {"link": "https://www.douban.com/people/tianchuan/", "name": "\u9521\u7f50\u5934"}}, {"rating": "4", "vote_num": "0", "author": {"link": "https://www.douban.com/people/45613020/", "name": "\u88c5X\u6c49\u7eb8\u5f20\u5927\u6bdb"}}, {"rating": "5", "vote_num": "0", "author": {"link": "https://www.douban.com/people/yemodao/", "name": "\u591c\u6469\u5200"}}, {"rating": "4", "vote_num": "0", "author": {"link": "https://www.douban.com/people/zuike/", "name": "\u5634\u5ba2"}}, {"rating": "4", "vote_num": "0", "author": {"link": "https://www.douban.com/people/46180980/", "name": "EVA_\u5f81\u670d\u5929\u5802"}}, {"rating": "4", "vote_num": "0", "author": {"link": "https://www.douban.com/people/2401259/", "name": "\u51b7\u51b7"}}, {"rating": "5", "vote_num": "0", "author": {"link": "https://www.douban.com/people/1159054/", "name": "\u5165"}}, {"rating": "5", "vote_num": "0", "author": {"link": "https://www.douban.com/people/yangisyang/", "name": "\u6768\u5b50\u865a"}}, {"rating": "5", "vote_num": "0", "author": {"link": "https://www.douban.com/people/yemodao/", "name": "\u591c\u6469\u5200"}}, {"rating": "4", "vote_num": "0", "author": {"link": "https://www.douban.com/people/zuike/", "name": "\u5634\u5ba2"}}, {"rating": "4", "vote_num": "0", "author": {"link": "https://www.douban.com/people/46180980/", "name": "EVA_\u5f81\u670d\u5929\u5802"}}, {"rating": "4", "vote_num": "0", "author": {"link": "https://www.douban.com/people/2401259/", "name": "\u51b7\u51b7"}}, {"rating": "5", "vote_num": "0", "author": {"link": "https://www.douban.com/people/1159054/", "name": "\u5165"}}, {"rating": "5", "vote_num": "0", "author": {"link": "https://www.douban.com/people/yangisyang/", "name": "\u6768\u5b50\u865a"}}, {"rating": "3", "vote_num": "0", "author": {"link": "https://www.douban.com/people/dtspsAli/", "name": "Patrick\u5cf0\u5cf0"}}, {"rating": "4", "vote_num": "0", "author": {"link": "https://www.douban.com/people/floathwusu/", "name": "\u9ec4\u65e0\u82cf"}}, {"rating": "5", "vote_num": "0", "author": {"link": "https://www.douban.com/people/49840485/", "name": "\u949f\u7b11\u4e42"}}, {"rating": "5", "vote_num": "0", "author": {"link": "https://www.douban.com/people/miaomiao1025/", "name": "\u96d5\u523b\u6642\u5149"}}, {"rating": "4", "vote_num": "0", "author": {"link": "https://www.douban.com/people/turandot0815/", "name": "=_=\u79cb\u53f6"}}, {"rating": "5", "vote_num": "0", "author": {"link": "https://www.douban.com/people/1122936/", "name": "\u4e00\u7247\u4e91"}}, {"rating": "3", "vote_num": "0", "author": {"link": "https://www.douban.com/people/zhangxiangyu_/", "name": "\u5927\u7ae0\u9c7c"}}, {"rating": "5", "vote_num": "0", "author": {"link": "https://www.douban.com/people/leonardoxue/", "name": "\u6d1b\u57ce\u514b\u543e"}}, {"rating": "4", "vote_num": "0", "author": {"link": "https://www.douban.com/people/1532705/", "name": "blb"}}, {"rating": "5", "vote_num": "0", "author": {"link": "https://www.douban.com/people/lizlee0601/", "name": "LizLee"}}, {"rating": "5", "vote_num": "0", "author": {"link": "https://www.douban.com/people/44078114/", "name": "static"}}, {"rating": "5", "vote_num": "0", "author": {"link": "https://www.douban.com/people/4073793/", "name": "\u9c7c\u513f"}}, {"rating": "4", "vote_num": "0", "author": {"link": "https://www.douban.com/people/terababy/", "name": "terababy"}}, {"rating": "4", "vote_num": "0", "author": {"link": "https://www.douban.com/people/2072165/", "name": "hui"}}, {"rating": "3", "vote_num": "0", "author": {"link": "https://www.douban.com/people/zhangxiangyu_/", "name": "\u5927\u7ae0\u9c7c"}}, {"rating": "5", "vote_num": "0", "author": {"link": "https://www.douban.com/people/leonardoxue/", "name": "\u6d1b\u57ce\u514b\u543e"}}, {"rating": "4", "vote_num": "0", "author": {"link": "https://www.douban.com/people/1532705/", "name": "blb"}}, {"rating": "5", "vote_num": "0", "author": {"link": "https://www.douban.com/people/lizlee0601/", "name": "LizLee"}}, {"rating": "5", "vote_num": "0", "author": {"link": "https://www.douban.com/people/44078114/", "name": "static"}}, {"rating": "5", "vote_num": "0", "author": {"link": "https://www.douban.com/people/4073793/", "name": "\u9c7c\u513f"}}, {"rating": "4", "vote_num": "0", "author": {"link": "https://www.douban.com/people/terababy/", "name": "terababy"}}, {"rating": "4", "vote_num": "0", "author": {"link": "https://www.douban.com/people/2072165/", "name": "hui"}}, {"rating": "5", "vote_num": "2", "author": {"link": "https://www.douban.com/people/Jane_1-29/", "name": "\u9999\u6c34\u74f6"}}, {"rating": "undefined", "vote_num": "0", "author": {"link": "https://www.douban.com/people/3288308/", "name": "\u795e\u5a46\u5c0f\u59d0"}}, {"rating": "4", "vote_num": "0", "author": {"link": "https://www.douban.com/people/rollin/", "name": "\u53c9\u53c9\u5c0f\u7bad\u732a"}}, {"rating": "4", "vote_num": "0", "author": {"link": "https://www.douban.com/people/3589989/", "name": "\u8679\u53e3\u4e00\u6761\u9f99"}}, {"rating": "5", "vote_num": "0", "author": {"link": "https://www.douban.com/people/troyluan/", "name": "\u4e71"}}, {"rating": "4", "vote_num": "0", "author": {"link": "https://www.douban.com/people/3479798/", "name": "\u74dc\u74dc\u4e0d\u7761\u89c9"}}, {"rating": "5", "vote_num": "5", "author": {"link": "https://www.douban.com/people/eve42/", "name": "Eve|Classified"}}, {"rating": "4", "vote_num": "0", "author": {"link": "https://www.douban.com/people/luwenhui/", "name": "\u9c81\u5927\u5e08"}}, {"rating": "4", "vote_num": "0", "author": {"link": "https://www.douban.com/people/31316178/", "name": "geek"}}, {"rating": "5", "vote_num": "0", "author": {"link": "https://www.douban.com/people/senz/", "name": "sen"}}, {"rating": "5", "vote_num": "0", "author": {"link": "https://www.douban.com/people/42030428/", "name": "\u6c89\u96e8\u6da6\u5fc3"}}, {"rating": "5", "vote_num": "0", "author": {"link": "https://www.douban.com/people/NG/", "name": "NG"}}, {"rating": "4", "vote_num": "0", "author": {"link": "https://www.douban.com/people/31316178/", "name": "geek"}}, {"rating": "5", "vote_num": "0", "author": {"link": "https://www.douban.com/people/senz/", "name": "sen"}}, {"rating": "5", "vote_num": "0", "author": {"link": "https://www.douban.com/people/42030428/", "name": "\u6c89\u96e8\u6da6\u5fc3"}}, {"rating": "5", "vote_num": "0", "author": {"link": "https://www.douban.com/people/NG/", "name": "NG"}}, {"rating": "4", "vote_num": "0", "author": {"link": "https://www.douban.com/people/minyee13/", "name": "minyee13"}}, {"rating": "5", "vote_num": "0", "author": {"link": "https://www.douban.com/people/nolike/", "name": "nolike"}}, {"rating": "4", "vote_num": "0", "author": {"link": "https://www.douban.com/people/masaikejun/", "name": "\u9a6c\u8d5b\u514b"}}, {"rating": "3", "vote_num": "0", "author": {"link": "https://www.douban.com/people/M.MixEr/", "name": "\u4eba\u7c7b\u5b66\u79d1\u7814\u7a76\u5458"}}, {"rating": "4", "vote_num": "0", "author": {"link": "https://www.douban.com/people/Zizou_Vam/", "name": "\u6258\u5c3c\u00b7\u738b\u5927\u62ff"}}, {"rating": "4", "vote_num": "0", "author": {"link": "https://www.douban.com/people/44021817/", "name": "Moriarty"}}, {"rating": "5", "vote_num": "0", "author": {"link": "https://www.douban.com/people/ilovehongkou/", "name": "\u80d6\u5f97\u6765\u8981\u620f"}}, {"rating": "4", "vote_num": "0", "author": {"link": "https://www.douban.com/people/54274563/", "name": "\u9ae6\u9ae6"}}, {"rating": "5", "vote_num": "0", "author": {"link": "https://www.douban.com/people/studentdao/", "name": "\u76d7\u76d7~"}}, {"rating": "4", "vote_num": "0", "author": {"link": "https://www.douban.com/people/54806925/", "name": "\u80e1\u6cfc\u7334"}}, {"rating": "5", "vote_num": "0", "author": {"link": "https://www.douban.com/people/yingjoy/", "name": "\u5de6\u557e\u557e"}}, {"rating": "5", "vote_num": "0", "author": {"link": "https://www.douban.com/people/feandy/", "name": "\u5b89\u72c4"}}, {"rating": "5", "vote_num": "0", "author": {"link": "https://www.douban.com/people/4585023/", "name": "\u4e50\u4e8b"}}, {"rating": "4", "vote_num": "0", "author": {"link": "https://www.douban.com/people/4653594/", "name": "Anti_Christ"}}, {"rating": "3", "vote_num": "0", "author": {"link": "https://www.douban.com/people/2644737/", "name": "zivin4"}}, {"rating": "4", "vote_num": "0", "author": {"link": "https://www.douban.com/people/Fe.douban/", "name": "\u5fc3\u4e4b\u65cb\u5f71"}}, {"rating": "4", "vote_num": "0", "author": {"link": "https://www.douban.com/people/4653594/", "name": "Anti_Christ"}}, {"rating": "3", "vote_num": "0", "author": {"link": "https://www.douban.com/people/2644737/", "name": "zivin4"}}, {"rating": "4", "vote_num": "0", "author": {"link": "https://www.douban.com/people/Fe.douban/", "name": "\u5fc3\u4e4b\u65cb\u5f71"}}, {"rating": "5", "vote_num": "0", "author": {"link": "https://www.douban.com/people/heyunchao007/", "name": "\u548c\u8fd0\u8d85"}}, {"rating": "5", "vote_num": "0", "author": {"link": "https://www.douban.com/people/xiaoyuxuan/", "name": "\u5c0f\u9c7c"}}, {"rating": "5", "vote_num": "0", "author": {"link": "https://www.douban.com/people/feizhuangzhuang/", "name": "\u80a5\u58ee\u58ee"}}, {"rating": "4", "vote_num": "0", "author": {"link": "https://www.douban.com/people/sylvialee2011/", "name": "sylvia lee"}}, {"rating": "3", "vote_num": "0", "author": {"link": "https://www.douban.com/people/2528691/", "name": "\u9ea6\u4e50\u811a"}}, {"rating": "5", "vote_num": "0", "author": {"link": "https://www.douban.com/people/zeroclan/", "name": "Zeroclan"}}, {"rating": "4", "vote_num": "0", "author": {"link": "https://www.douban.com/people/tiaoyuedepangzi/", "name": "\u80d6\u8df3\u8df3"}}, {"rating": "3", "vote_num": "0", "author": {"link": "https://www.douban.com/people/princeW/", "name": "PrinceW"}}, {"rating": "3", "vote_num": "0", "author": {"link": "https://www.douban.com/people/jshippo/", "name": "\u5927\u6cb3\u9a6c"}}, {"rating": "3", "vote_num": "0", "author": {"link": "https://www.douban.com/people/wizwood/", "name": "Vera"}}, {"rating": "4", "vote_num": "0", "author": {"link": "https://www.douban.com/people/imoviekobe/", "name": "\u6b63\u4e49B\u80dc"}}, {"rating": "4", "vote_num": "0", "author": {"link": "https://www.douban.com/people/49062903/", "name": "\u8fb0\u661f\u796d"}}, {"rating": "4", "vote_num": "0", "author": {"link": "https://www.douban.com/people/3266143/", "name": "\u83ab\u4e91\u8f69"}}, {"rating": "4", "vote_num": "2", "author": {"link": "https://www.douban.com/people/jeffersontang/", "name": "\u674e\u7136"}}, {"rating": "4", "vote_num": "0", "author": {"link": "https://www.douban.com/people/yuanlaishiximen/", "name": "\u539f\u6765\u662f\u897f\u95e8\u5927\u5b98\u4eba"}}, {"rating": "5", "vote_num": "0", "author": {"link": "https://www.douban.com/people/c541223724/", "name": "\u897f\u51b3"}}, {"rating": "5", "vote_num": "0", "author": {"link": "https://www.douban.com/people/liebsteprettywa/", "name": "\u535a\u535a\u7ef4\u5947"}}, {"rating": "4", "vote_num": "0", "author": {"link": "https://www.douban.com/people/3266143/", "name": "\u83ab\u4e91\u8f69"}}, {"rating": "4", "vote_num": "2", "author": {"link": "https://www.douban.com/people/jeffersontang/", "name": "\u674e\u7136"}}, {"rating": "4", "vote_num": "0", "author": {"link": "https://www.douban.com/people/yuanlaishiximen/", "name": "\u539f\u6765\u662f\u897f\u95e8\u5927\u5b98\u4eba"}}, {"rating": "5", "vote_num": "0", "author": {"link": "https://www.douban.com/people/c541223724/", "name": "\u897f\u51b3"}}, {"rating": "5", "vote_num": "0", "author": {"link": "https://www.douban.com/people/liebsteprettywa/", "name": "\u535a\u535a\u7ef4\u5947"}}, {"rating": "5", "vote_num": "0", "author": {"link": "https://www.douban.com/people/zl0072004/", "name": "\u53f2\u8482\u82ac\u5f20"}}, {"rating": "5", "vote_num": "0", "author": {"link": "https://www.douban.com/people/zhengeL/", "name": "\u90d110"}}, {"rating": "3", "vote_num": "0", "author": {"link": "https://www.douban.com/people/daliaodelinju/", "name": "\u5927\u6f66"}}, {"rating": "4", "vote_num": "0", "author": {"link": "https://www.douban.com/people/yeshunjia/", "name": "\u5357\u689d\u67d0\u8449"}}, {"rating": "3", "vote_num": "0", "author": {"link": "https://www.douban.com/people/11882042/", "name": "fence2004"}}, {"rating": "5", "vote_num": "1", "author": {"link": "https://www.douban.com/people/brokewing/", "name": "ForMyGirl"}}, {"rating": "5", "vote_num": "21", "author": {"link": "https://www.douban.com/people/jr.pimp/", "name": "Jr.Pimp"}}, {"rating": "4", "vote_num": "0", "author": {"link": "https://www.douban.com/people/32251971/", "name": "Bright"}}, {"rating": "4", "vote_num": "0", "author": {"link": "https://www.douban.com/people/qpCYU/", "name": "\u9a91\u58eb\u7684\u8499\u592a\u5947"}}, {"rating": "4", "vote_num": "0", "author": {"link": "https://www.douban.com/people/2849243/", "name": "shininglove"}}, {"rating": "5", "vote_num": "0", "author": {"link": "https://www.douban.com/people/Cherry.Pluto/", "name": "\u897f\u6728\u30a6\u30cb\u30b3"}}, {"rating": "5", "vote_num": "0", "author": {"link": "https://www.douban.com/people/Tokay/", "name": "\u94c1\u76ae\u9a91\u58eb"}}, {"rating": "4", "vote_num": "0", "author": {"link": "https://www.douban.com/people/45806509/", "name": "\u7f57\u963f\u5207\u5229"}}, {"rating": "5", "vote_num": "0", "author": {"link": "https://www.douban.com/people/y328675858/", "name": "\u79c1\u623f\u6b4c"}}, {"rating": "3", "vote_num": "0", "author": {"link": "https://www.douban.com/people/cooloh/", "name": "\u767d\u732b\u8b66\u957f"}}], "information": {"language": ["\u82f1\u8bed"], "country": ["\u7f8e\u56fd"], "actor": ["\u7ea6\u7ff0\u00b7\u7279\u62c9\u6c83\u5c14\u5854", "\u5c3c\u53e4\u62c9\u65af\u00b7\u51ef\u5947", "\u743c\u00b7\u827e\u4f26", "\u4e9a\u5386\u6851\u5fb7\u7f57\u00b7\u5c3c\u6c83\u62c9", "\u5409\u5a1c\u00b7\u683c\u7533", "\u591a\u7c73\u5c3c\u514b\u00b7\u65af\u4e07", "\u5c3c\u514b\u00b7\u5361\u7d22\u7ef4\u8328", "\u54c8\u5a01\u00b7\u666e\u96f7\u65af\u5185\u5c14", "\u79d1\u9c81\u59c6\u00b7\u8d39\u5965\u745e", "\u7ea6\u7ff0\u00b7\u5361\u6d1b\u00b7\u6797\u5947", "\u5e0c\u00b7\u5e9e\u5fb7", "\u7f57\u4f2f\u7279\u00b7\u7ef4\u65af\u591a\u59c6", "\u8d75\u7261\u4e39", "\u8a79\u59c6\u65af\u00b7\u4e39\u987f", "\u9a6c\u7279\u00b7\u7f57\u65af", "\u514b\u91cc\u65af\u00b7\u9c8d\u5c14", "Myles Jeffrey", "David McCurley", "\u6258\u9a6c\u65af\u00b7\u7b80", "\u6c64\u7c73\u00b7\u5f17\u62c9\u7eb3\u6839", "Dana Smith", "Romy Windsor", "\u4fdd\u7f57\u2022\u5e0c\u666e", "\u67ef\u514b\u00b7\u9c8d\u5179", "Lauren Sinclair", "\u672c\u00b7\u91cc\u5fb7", "Lisa Boyle", "Linda Hoffman", "\u4e39\u5c3c\u00b7\u9a6c\u65af\u7279\u68ee", "Michael Rocha"], "director": ["\u5434\u5b87\u68ee"], "alias": ["\u593a\u9762\u53cc\u96c4"], "length": ["138\u5206\u949f"], "imdb": "http://www.imdb.com/title/tt0119094", "time": ["1997-06-27(\u7f8e\u56fd)"], "type": ["\u52a8\u4f5c", "\u79d1\u5e7b", "\u72af\u7f6a"], "screenwriter": ["\u9ea6\u514b\u00b7\u97e6\u67cf", "\u8fc8\u514b\u5c14\u00b7\u79d1\u62c9\u91cc"]}, "photo": [{"src": "https://img3.doubanio.com/view/photo/albumicon/public/p767921303.jpg", "alt": "\u56fe\u7247", "ref": "https://movie.douban.com/photos/photo/767921303/"}, {"src": "https://img1.doubanio.com/view/photo/albumicon/public/p2352844417.jpg", "alt": "\u56fe\u7247", "ref": "https://movie.douban.com/photos/photo/2352844417/"}, {"src": "https://img1.doubanio.com/view/photo/albumicon/public/p2352844407.jpg", "alt": "\u56fe\u7247", "ref": "https://movie.douban.com/photos/photo/2352844407/"}, {"src": "https://img1.doubanio.com/view/photo/albumicon/public/p2352844379.jpg", "alt": "\u56fe\u7247", "ref": "https://movie.douban.com/photos/photo/2352844379/"}, {"src": "https://img3.doubanio.com/view/photo/albumicon/public/p2352844375.jpg", "alt": "\u56fe\u7247", "ref": "https://movie.douban.com/photos/photo/2352844375/"}], "name": "\u53d8\u8138 Face/Off", "poster": ["https://img3.doubanio.com/view/movie_poster_cover/ipst/public/p2173855883.jpg"], "review": [{"rating": "5", "author": {"link": "https://www.douban.com/people/mxl117/", "name": "\u5341\u4e00\u6708\u7684\u96e8"}, "title": {"link": "https://movie.douban.com/review/1165222/", "name": "\u6559\u5802,\u767d\u9e3d,\u5b50\u5f39,\u8840\u82b1\uff0d\uff0d\uff0d\u631a\u7231\u00b7\u53d8\u8138"}}, {"rating": "4", "author": {"link": "https://www.douban.com/people/moredarkwhite/", "name": "\u66f4\u6df1\u7684\u767d\u8272"}, "title": {"link": "https://movie.douban.com/review/4948567/", "name": "\u5434\u5b87\u68ee\u7684\u6700\u9ad8\u5cf0"}}, {"rating": "4", "author": {"link": "https://www.douban.com/people/doudou-su/", "name": "\u8c46\u8c46\u9165"}, "title": {"link": "https://movie.douban.com/review/5980454/", "name": "\u90a3\u4e2a\u5370\u8c61\u6df1\u523b\u7684\u9ed1\u9053\u5973\u5b50"}}, {"rating": "5", "author": {"link": "https://www.douban.com/people/90548304/", "name": "\u6e05\u6668\u5fae\u98a8"}, "title": {"link": "https://movie.douban.com/review/7571502/", "name": "\u582a\u79f0\u5434\u5b87\u68ee\u5bfc\u6f14\u66b4\u529b\u6d6a\u6f2b\u7f8e\u5b66\u7ecf\u5178\u4f5c\u54c1"}}, {"rating": "3", "author": {"link": "https://www.douban.com/people/3178514/", "name": "\u76ee\u6b4c"}, "title": {"link": "https://movie.douban.com/review/1562462/", "name": "\u88ab\u53d6\u4ee3\u7684\u897f\u6069"}}, {"rating": "5", "author": {"link": "https://www.douban.com/people/kellylovekelly/", "name": "\u7433\u7433//\u5c0f\u9c7c\u5b50"}, "title": {"link": "https://movie.douban.com/review/1018792/", "name": "face off"}}, {"rating": "5", "author": {"link": "https://www.douban.com/people/littleAI/", "name": "\u2602K\u5144\u2665"}, "title": {"link": "https://movie.douban.com/review/1325332/", "name": "\u89c9\u5f97\u7ea6\u7ff0\u2022\u7279\u62c9\u6c83\u5854\u66f4\u51fa\u5f69"}}, {"rating": "5", "author": {"link": "https://www.douban.com/people/dugurui/", "name": "dugurui"}, "title": {"link": "https://movie.douban.com/review/1009025/", "name": "John Woo\u98a0\u5cf0\u4e4b\u4f5c"}}, {"rating": "5", "author": {"link": "https://www.douban.com/people/77096703/", "name": "\u9648\u8fdc\u8fdc"}, "title": {"link": "https://movie.douban.com/review/7675306/", "name": "\u53d8\u8138\u5f71\u8bc4\u2014\u2014\u4e00\u51fa\u4e0d\u6015\u5267\u900f\u7684\u597d\u620f"}}, {"rating": "5", "author": {"link": "https://www.douban.com/people/cantabile/", "name": "[\u5df2\u6ce8\u9500]"}, "title": {"link": "https://movie.douban.com/review/3217286/", "name": "\u4e2d\u56fd\u5143\u7d20\u3002\u3002\u3002"}}, {"rating": "4", "author": {"link": "https://www.douban.com/people/xiaobaohys/", "name": "\u6843\u82b1\u5c9b\u50bb\u59d1"}, "title": {"link": "https://movie.douban.com/review/2295065/", "name": "\u53ea\u662f\u8fc7\u763e"}}, {"rating": "4", "author": {"link": "https://www.douban.com/people/milamila/", "name": "\u67ab\u4e00\u6837\u7684\u6210\u957f"}, "title": {"link": "https://movie.douban.com/review/1565702/", "name": "\u4e9a\u5f53\u7684\u968f\u8eab\u542c"}}, {"rating": "5", "author": {"link": "https://www.douban.com/people/1394285/", "name": "\u732b\u5c0fN"}, "title": {"link": "https://movie.douban.com/review/1646790/", "name": "\u597d\u4eba\u4e0e\u574f\u4eba"}}, {"rating": "5", "author": {"link": "https://www.douban.com/people/2079970/", "name": "\u5fc3\u91cc\u6709\u4e2a\u9b54\u9b3c"}, "title": {"link": "https://movie.douban.com/review/1256428/", "name": "\u600e\u4e48\u4e0d\u597d\uff01\uff01\uff01\uff01\uff01\uff01\uff01"}}, {"rating": "3", "author": {"link": "https://www.douban.com/people/maverick0806/", "name": "Maverick"}, "title": {"link": "https://movie.douban.com/review/6284171/", "name": "\u300a\u53d8\u8138\u300b\u7535\u5f71\u5267\u672c"}}, {"rating": "5", "author": {"link": "https://www.douban.com/people/1513326/", "name": "\u73ca\u745a\u87f2\u87f2\u2665"}, "title": {"link": "https://movie.douban.com/review/1264232/", "name": "\u82f1\u96c4\u662f\u4e0d\u5b58\u5728\u773c\u6dda\uff1f"}}, {"rating": "5", "author": {"link": "https://www.douban.com/people/russelrain/", "name": "Bow"}, "title": {"link": "https://movie.douban.com/review/1146561/", "name": "\u5434\u5b87\u68ee\u7684\u9e3d\u5b50\u9732\u4e86\u9985\u513f"}}, {"rating": "3", "author": {"link": "https://www.douban.com/people/danjx/", "name": "\u4e0d\u5982\u76f8\u5fd8\u4e8e\u6c5f\u6e56"}, "title": {"link": "https://movie.douban.com/review/1254068/", "name": "\u7ffb\u62cd\u7684\u82f1\u96c4\u672c\u8272"}}, {"rating": "4", "author": {"link": "https://www.douban.com/people/yishu./", "name": "\u4ea6\u6811"}, "title": {"link": "https://movie.douban.com/review/7395492/", "name": "\u5584\u6076\u7684\u7ef4\u5ea6"}}, {"rating": "2", "author": {"link": "https://www.douban.com/people/64498293/", "name": "\u6a58\u6797\u5c9b"}, "title": {"link": "https://movie.douban.com/review/6747390/", "name": "\u4e0d\u662f\u5f71\u8bc4\uff0c\u53ea\u662f\u77ed\u8bc4\u4e0d\u591f"}}, {"rating": "5", "author": {"link": "https://www.douban.com/people/6328459/", "name": "\u00a7dudu\u00a7"}, "title": {"link": "https://movie.douban.com/review/6590042/", "name": "\u955c\u5b50\u91cc\u7684\u81ea\u6211\uff0c\u865a\u5047\u800c\u53c8\u771f\u5b9e"}}, {"rating": "5", "author": {"link": "https://www.douban.com/people/13444468/", "name": "\u4e0b\u96e8\u5929\u7684\u5c0f\u72d7"}, "title": {"link": "https://movie.douban.com/review/6526789/", "name": "\u4eba\u6027"}}, {"rating": "5", "author": {"link": "https://www.douban.com/people/DnASort/", "name": "\u9752\u7fce\u9876"}, "title": {"link": "https://movie.douban.com/review/5984903/", "name": "\u591c\u5e02"}}, {"rating": "4", "author": {"link": "https://www.douban.com/people/40174273/", "name": "\u6070\u6070"}, "title": {"link": "https://movie.douban.com/review/7932711/", "name": "\u4e92\u6362\u8eab\u4efd\u624d\u80fd\u4f53\u9a8c\u522b\u6837\u751f\u6d3b\uff1f"}}, {"rating": "5", "author": {"link": "https://www.douban.com/people/124379241/", "name": "Funny \\"}, "title": {"link": "https://movie.douban.com/review/7777168/", "name": "Face Of"}}, {"rating": "5", "author": {"link": "https://www.douban.com/people/owenloi/", "name": "Owen-LOi"}, "title": {"link": "https://movie.douban.com/review/7323167/", "name": "Nice Face"}}, {"rating": "5", "author": {"link": "https://www.douban.com/people/79601104/", "name": "violet"}, "title": {"link": "https://movie.douban.com/review/6825208/", "name": "\u523a\u6fc0\uff0c\u8d85\u8d5e"}}, {"rating": "4", "author": {"link": "https://www.douban.com/people/Resphoina_/", "name": "His-Tory"}, "title": {"link": "https://movie.douban.com/review/5648875/", "name": "Face/Off"}}, {"rating": "4", "author": {"link": "https://www.douban.com/people/yvonn/", "name": "[\u5df2\u6ce8\u9500]"}, "title": {"link": "https://movie.douban.com/review/2799922/", "name": "\u7ba1\u4e2d\u7aa5\u8c79"}}, {"rating": "3", "author": {"link": "https://www.douban.com/people/4483365/", "name": "\u6e29\u6668"}, "title": {"link": "https://movie.douban.com/review/2097891/", "name": "[\u53d8\u8138]\u2014\u2014\u597d\u83b1\u575e\u4f53\u5236\u4e0b\u7684\u4e00\u573a\u6e2f\u5473\u9a73\u706b"}}, {"rating": "4", "author": {"link": "https://www.douban.com/people/2152014/", "name": "\u5929\u4e0b\u4e4c\u9e26\u4e00\u822c\u9ed1"}, "title": {"link": "https://movie.douban.com/review/1558219/", "name": "\u8001\u5434+2\u7537\u4e3b"}}, {"rating": "5", "author": {"link": "https://www.douban.com/people/43130402/", "name": "\u91ca\u653e\u7e41\u534e"}, "title": {"link": "https://movie.douban.com/review/7769056/", "name": "\u66b4\u529b\u5916\u8868\u4e0b\u63a2\u8ba8\u4eba\u6027"}}, {"rating": "5", "author": {"link": "https://www.douban.com/people/57093382/", "name": "\u5ba5\u6db5"}, "title": {"link": "https://movie.douban.com/review/7666609/", "name": "face off"}}, {"rating": "4", "author": {"link": "https://www.douban.com/people/70950231/", "name": "\u6c34\u56de"}, "title": {"link": "https://movie.douban.com/review/7659586/", "name": "\u53d8\u8138"}}, {"rating": "3", "author": {"link": "https://www.douban.com/people/51586911/", "name": "\u82a5\u821f"}, "title": {"link": "https://movie.douban.com/review/7200446/", "name": "\u731c\u7591\u3001\u6492\u8c0e\u3001\u8d8a\u6765\u8d8a\u50cf\u5a5a\u59fb\u4e86."}}, {"rating": "4", "author": {"link": "https://www.douban.com/people/70053575/", "name": "\u6d6e\u5f71\u4eba\u751f"}, "title": {"link": "https://movie.douban.com/review/7166602/", "name": "\u8001\u7535\u5f71\u8001\u60c5\u6000"}}, {"rating": "5", "author": {"link": "https://www.douban.com/people/93438147/", "name": "\u613f\u96e8\u98de\u626c"}, "title": {"link": "https://movie.douban.com/review/7156448/", "name": "\u5dc5\u5cf0\u5bf9\u51b3"}}, {"rating": "4", "author": {"link": "https://www.douban.com/people/70293659/", "name": "Thomas"}, "title": {"link": "https://movie.douban.com/review/6960516/", "name": "\u6c5f\u6e56\u60c5"}}, {"rating": "5", "author": {"link": "https://www.douban.com/people/50576284/", "name": "\u4e0d\u518d\u662f\u5948\u95e8\u6469\u5c14"}, "title": {"link": "https://movie.douban.com/review/5990601/", "name": "\u5411\u6765\u6ca1\u6807\u9898"}}, {"rating": "5", "author": {"link": "https://www.douban.com/people/15097768/", "name": "\u5f71\u5b50"}, "title": {"link": "https://movie.douban.com/review/6498596/", "name": "\u300a\u53d8\u8138\u300b\uff1a\u5584\u6076\u65e0\u95f4\u2014\u2014\u52a8\u4f5c\u7247\u91cc\u7684\u7edd\u5531"}}, {"rating": "3", "author": {"link": "https://www.douban.com/people/52823989/", "name": "WelcomeLee"}, "title": {"link": "https://movie.douban.com/review/5922079/", "name": "\u4e00\u4e2a\u610f\u5473\u6df1\u957f\u7684\u955c\u5934"}}, {"rating": "5", "author": {"link": "https://www.douban.com/people/38981529/", "name": "tia "}, "title": {"link": "https://movie.douban.com/review/5329986/", "name": "\u53d1\u73b0\u4e86\u8fd9\u90e8\u7535\u5f71\u7684\u4e00\u4e2a\u758f\u5ffd\u70b9\u3002"}}, {"rating": "5", "author": {"link": "https://www.douban.com/people/47566846/", "name": "\u4e54\u4e09\u5343"}, "title": {"link": "https://movie.douban.com/review/4486246/", "name": "\u6e2f\u7f8e\u7684\u5b8c\u7f8e\u7ed3\u5408"}}, {"rating": "5", "author": {"link": "https://www.douban.com/people/2211481/", "name": "Angeler"}, "title": {"link": "https://movie.douban.com/review/2935475/", "name": "\u4e3a\u7535\u5f71\u800c\u751f"}}, {"rating": "5", "author": {"link": "https://www.douban.com/people/2665618/", "name": "\u81ed\u81ed\u9ece\u5b50"}, "title": {"link": "https://movie.douban.com/review/1480183/", "name": "\u6b63\u4e0e\u90aa\u7684\u535a\u5f08"}}, {"rating": "4", "author": {"link": "https://www.douban.com/people/zhroay/", "name": "\u674e\u666e\u66fc"}, "title": {"link": "https://movie.douban.com/review/1437584/", "name": "\u53c8\u89c1\u9e3d\u5b50\u98de\u8d77"}}, {"rating": "4", "author": {"link": "https://www.douban.com/people/aliceindreams/", "name": "\u5218\u660e\u9525"}, "title": {"link": "https://movie.douban.com/review/1190812/", "name": "\u6df1\u5c42\u7684\u5b58\u5728"}}, {"rating": "5", "author": {"link": "https://www.douban.com/people/Citytiger/", "name": "CityTiger"}, "title": {"link": "https://movie.douban.com/review/1049424/", "name": "\u8d85\u8d8a\u53d8\u8138\uff0c\u8001\u5434\u5c06\u6210\u4e3a\u5927\u5e08\uff01"}}, {"rating": "5", "author": {"link": "https://www.douban.com/people/figue/", "name": "Pac\u00b2o"}, "title": {"link": "https://movie.douban.com/review/1029286/", "name": "\u529b\u8350\u4e0e\u63a8\u8350\u4e4b\u95f4\u7684\u5f98\u5f8a"}}, {"rating": "4", "author": {"link": "https://www.douban.com/people/sucencen/", "name": "sucencen"}, "title": {"link": "https://movie.douban.com/review/1013799/", "name": "\uff08\u65e0\u6807\u9898\uff09"}}, {"rating": "4", "author": {"link": "https://www.douban.com/people/115837160/", "name": "\u6e29\u6696\u7684\u5a01\u5c14\u4f2f"}, "title": {"link": "https://movie.douban.com/review/7916945/", "name": "\u70c8\u9152\u4e0e\u6d53\u8336"}}, {"rating": "5", "author": {"link": "https://www.douban.com/people/73666911/", "name": "\u83b9\u96ea\u6674\u7a7a"}, "title": {"link": "https://movie.douban.com/review/7865758/", "name": "\u5927\u6982\u8fd9\u5c31\u662f\u76f8\u7231\u76f8\u6740\u3002\u3002\u3002"}}, {"rating": "3", "author": {"link": "https://www.douban.com/people/63440066/", "name": "\u8eb2\u96e8\u7684\u5c4b\u6a90"}, "title": {"link": "https://movie.douban.com/review/7544191/", "name": "\u300a\u53d8\u8138\u300b\u2014\u2014\u4f5c\u8005\u7535\u5f71\u98ce\u683c\u5316\u7684\u7f8e\u5b66\u8ffd\u6c42"}}, {"rating": "4", "author": {"link": "https://www.douban.com/people/53855811/", "name": "\u65c5\u884c\u8005"}, "title": {"link": "https://movie.douban.com/review/6752405/", "name": "(53) Face Off"}}, {"rating": "5", "author": {"link": "https://www.douban.com/people/2457791/", "name": "\u51ac\u7166"}, "title": {"link": "https://movie.douban.com/review/5592353/", "name": "\u54e5"}}, {"rating": "5", "author": {"link": "https://www.douban.com/people/53568039/", "name": "\u5ce8\u7709\u5c71\u625b\u628a\u5b50"}, "title": {"link": "https://movie.douban.com/review/5292070/", "name": "\u7ea6\u7ff0\u7279\u62c9\u6c83\u5c14\u5854\u7684\u6e29\u67d4\u548c\u53e4\u60d1"}}, {"rating": "3", "author": {"link": "https://www.douban.com/people/34263550/", "name": "\u6a31\u6843\u6811\u4e0a\u6a31\u6843\u7ea2"}, "title": {"link": "https://movie.douban.com/review/4569431/", "name": "\u53d8\u8138\u7684\u955c\u50cf~"}}, {"rating": "4", "author": {"link": "https://www.douban.com/people/bamboo1988/", "name": "\u7af9\u5b50"}, "title": {"link": "https://movie.douban.com/review/3593510/", "name": "cage\u5927\u795e"}}, {"rating": "3", "author": {"link": "https://www.douban.com/people/15019040/", "name": "Annie"}, "title": {"link": "https://movie.douban.com/review/3125658/", "name": "After\u300a\u53d8\u8138\u300b\uff1a\u6765\u6765\u6765 \u6211\u4eec\u6765\u603b\u7ed3\u4e00\u4e0b"}}, {"rating": "5", "author": {"link": "https://www.douban.com/people/4278056/", "name": "eleveno"}, "title": {"link": "https://movie.douban.com/review/2310196/", "name": "\u7279\u62c9\u6c83\u5c14\u5854"}}, {"rating": "4", "author": {"link": "https://www.douban.com/people/immortal_3/", "name": "\u4ea2\u8499"}, "title": {"link": "https://movie.douban.com/review/2013637/", "name": "\u300a\u8eab\u4efd\u626e\u6f14\u7684\u4e50\u8da3\u300b"}}, {"rating": "4", "author": {"link": "https://www.douban.com/people/3156886/", "name": "\u590f\u8bed\u51b0"}, "title": {"link": "https://movie.douban.com/review/1546254/", "name": "\u809a\u8169"}}, {"rating": "5", "author": {"link": "https://www.douban.com/people/ohmyboy/", "name": "\u72d7\u5d3d\u7684\u4e3b\u4eba"}, "title": {"link": "https://movie.douban.com/review/1543601/", "name": "\u5434\u5b87\u68ee\uff0c\u8ba9\u4eba\u63a5\u53d7\u4e0d\u4e86\u7684\u8111\u888b"}}, {"rating": "4", "author": {"link": "https://www.douban.com/people/1498740/", "name": "\u5c0f\u8001\u5e7a"}, "title": {"link": "https://movie.douban.com/review/1490609/", "name": "Face Off"}}, {"rating": "5", "author": {"link": "https://www.douban.com/people/1011305/", "name": "[\u5df2\u6ce8\u9500]"}, "title": {"link": "https://movie.douban.com/review/1468104/", "name": "\u6211\u6240\u77e5\u9053\u7684\u90e8\u5206\u7ec6\u8282"}}, {"rating": "4", "author": {"link": "https://www.douban.com/people/charlot_te/", "name": "Eh bien"}, "title": {"link": "https://movie.douban.com/review/1232043/", "name": "\u65e0\u9898"}}, {"rating": "4", "author": {"link": "https://www.douban.com/people/fig/", "name": "fig"}, "title": {"link": "https://movie.douban.com/review/1031028/", "name": "\u770b\u4e0d\u4e86\u4e09\u904d"}}, {"rating": "4", "author": {"link": "https://www.douban.com/people/33067351/", "name": "lilei"}, "title": {"link": "https://movie.douban.com/review/8117661/", "name": "\u5176\u5b9e\u6211\u662f\u4e2a\u6f14\u5458"}}, {"rating": "4", "author": {"link": "https://www.douban.com/people/seayo/", "name": "\u7231\u8354\u601d"}, "title": {"link": "https://movie.douban.com/review/8116704/", "name": "\u5434\u5b87\u68ee\u7684\u767d\u9e3d\uff0c\u662f\u85cf\u5728\u66b4\u529b\u4e2d\u7684\u7eaf\u6d01\u548c\u5e73"}}, {"rating": "3", "author": {"link": "https://www.douban.com/people/78715446/", "name": "\u9ed1\u9762\u9f99\u738b"}, "title": {"link": "https://movie.douban.com/review/8089434/", "name": "\u79d1\u5e7b\u610f\u4e49\u4e0a\u7684\u8b66\u532a\u7247"}}, {"rating": "4", "author": {"link": "https://www.douban.com/people/127051443/", "name": "\u5f20\u65e0\u8da3"}, "title": {"link": "https://movie.douban.com/review/8079582/", "name": "\u6bcf\u4e00\u90e8\u7535\u5f71\u90fd\u5728\u547c\u5524\u7231"}}, {"rating": "5", "author": {"link": "https://www.douban.com/people/115131162/", "name": "\u6ee1\u6708"}, "title": {"link": "https://movie.douban.com/review/8070750/", "name": "\u6210\u5168\u53d8\u8138\u4f73\u7247\u5730\u4f4d\u7684\u4e0d\u662f\u6545\u4e8b\u672c\u8eab\uff0c\u800c\u662f\u6f14\u5458\u7684\u6f14\u6280"}}, {"rating": "4", "author": {"link": "https://www.douban.com/people/54855714/", "name": "\u98ce\u96e8\u98d8\u5bd2\u70df\u7fe0"}, "title": {"link": "https://movie.douban.com/review/8047799/", "name": "\u5434\u5b87\u68ee\u7684\u624d\u534e"}}, {"rating": "5", "author": {"link": "https://www.douban.com/people/65988896/", "name": "\u79be\u5931\u8349\u51e1"}, "title": {"link": "https://movie.douban.com/review/5649006/", "name": "\u4e24\u4f4d\u5b9e\u529b\u6d3e\u6f14\u5458\u7684\u5b8c\u7f8e\u6f14\u51fa"}}, {"rating": "5", "author": {"link": "https://www.douban.com/people/61784034/", "name": "\u51a0\u8861\u54e5"}, "title": {"link": "https://movie.douban.com/review/5633901/", "name": "\u597d\u83b1\u575e\u7684\u5434\u6c0f\u66b4\u529b\u7f8e\u5b66"}}, {"rating": "4", "author": {"link": "https://www.douban.com/people/60063967/", "name": "\u4e0a\u5c09\u8bd7\u4eba"}, "title": {"link": "https://movie.douban.com/review/5616087/", "name": "\u8d5e\uff0c\u7ecf\u5178\u7684\u5434\u6c0f\u98ce\u683c"}}, {"rating": "4", "author": {"link": "https://www.douban.com/people/liuchm868/", "name": "\u7535\u5f71\u751f\u6d3b"}, "title": {"link": "https://movie.douban.com/review/5595354/", "name": "\u5c3c\u53e4\u62c9\u65af\u51ef\u5947\u7684\u6f14\u6280\u4ee4\u4eba\u53f9\u670d"}}, {"rating": "5", "author": {"link": "https://www.douban.com/people/Poetess/", "name": "Poetess"}, "title": {"link": "https://movie.douban.com/review/5486262/", "name": "\u5199\u7ed915\u5e74\u540e\u7684Face/Off"}}, {"rating": "5", "author": {"link": "https://www.douban.com/people/51616699/", "name": "jie"}, "title": {"link": "https://movie.douban.com/review/5343897/", "name": "\u7ecf\u5178\u4e2d\u7684\u7ecf\u5178"}}, {"rating": "4", "author": {"link": "https://www.douban.com/people/81513380/", "name": "\u65e0\u6cd5\u8de8\u8d8a\u7684\u9e3f\u6c9f"}, "title": {"link": "https://movie.douban.com/review/7301479/", "name": "\u66b4\u529b\u7f8e\u5b66"}}, {"rating": "5", "author": {"link": "https://www.douban.com/people/momoko1024/", "name": "\u6cab\u6cab\u5361"}, "title": {"link": "https://movie.douban.com/review/5301297/", "name": "\u5bf9\u5f97\u8d77\uff1a\u767d\u9e3d\u6bbf\u5802\u7ea7"}}, {"rating": "4", "author": {"link": "https://www.douban.com/people/evilwei/", "name": "evilwei"}, "title": {"link": "https://movie.douban.com/review/5284411/", "name": "\u53d8\u8138"}}, {"rating": "4", "author": {"link": "https://www.douban.com/people/48924562/", "name": "IORI"}, "title": {"link": "https://movie.douban.com/review/5233545/", "name": "\u98ce\u4e91\u9645\u4f1a"}}, {"rating": "5", "author": {"link": "https://www.douban.com/people/innerw/", "name": "\u5c0f\u5de6"}, "title": {"link": "https://movie.douban.com/review/5219895/", "name": "\u53d8\u8138\u4e0d\u53d8\u5fc3"}}, {"rating": "3", "author": {"link": "https://www.douban.com/people/56929816/", "name": "\u8c46\u74e3\u597d\u96be\u7528"}, "title": {"link": "https://movie.douban.com/review/5209540/", "name": "\u5267\u60c5\u6709\u6f0f\u6d1e\uff1f"}}, {"rating": "4", "author": {"link": "https://www.douban.com/people/isoh/", "name": "\u6b27\u704f\u9e9f"}, "title": {"link": "https://movie.douban.com/review/5203890/", "name": "\u6e2f\u5f0f\u897f\u9910\uff0c\u2014\u2014\u6d45\u8bc4\u300c\u53d8\u8138\u300d\u4e4b\u9999\u6e2f\u4e0e\u597d\u83b1\u575e\u5143\u7d20..."}}, {"rating": "3", "author": {"link": "https://www.douban.com/people/tuweri/", "name": "tuweri"}, "title": {"link": "https://movie.douban.com/review/5199302/", "name": "Face/Off"}}, {"rating": "4", "author": {"link": "https://www.douban.com/people/mengmengdong/", "name": "\u73b2\u73d1"}, "title": {"link": "https://movie.douban.com/review/5120611/", "name": "\u5267\u60c5\u5b89\u6392\u7ec6\u81f4\u5165\u5fae\u3001\u4ea6\u6b63\u4ea6\u90aa\u5c3c\u53e4\u62c9\u65af"}}, {"rating": "4", "author": {"link": "https://www.douban.com/people/54003699/", "name": "\u4e91\u6de1\u98ce\u8f7b"}, "title": {"link": "https://movie.douban.com/review/5093040/", "name": "\u6211\u80fd\u8ba4\u5f97\u4f60"}}, {"rating": "4", "author": {"link": "https://www.douban.com/people/47446958/", "name": "hychaz"}, "title": {"link": "https://movie.douban.com/review/5087130/", "name": "\u53c8\u89c1\u66b4\u529b\u7f8e\u5b66"}}, {"rating": "4", "author": {"link": "https://www.douban.com/people/39376875/", "name": "\u5411\u5c0f\u8c46"}, "title": {"link": "https://movie.douban.com/review/5060030/", "name": "\u4e4d\u6cc4\u7684\u67d4\u60c5"}}, {"rating": "4", "author": {"link": "https://www.douban.com/people/chairmannirvana/", "name": "\u6d85\u74e6\u7eb3"}, "title": {"link": "https://movie.douban.com/review/5038532/", "name": "Face/Off"}}, {"rating": "5", "author": {"link": "https://www.douban.com/people/zhangtianbo/", "name": "hysoka"}, "title": {"link": "https://movie.douban.com/review/5024066/", "name": "Face off"}}, {"rating": "5", "author": {"link": "https://www.douban.com/people/jocelynhp/", "name": "\u662f\u5305\u5b50\u4e0d\u662f\u998d\u998d"}, "title": {"link": "https://movie.douban.com/review/5020238/", "name": "\u66b4\u529b\u7f8e\u5b66\u4ec0\u4e48\u7684"}}, {"rating": "4", "author": {"link": "https://www.douban.com/people/kaizz5158/", "name": "\u90d1\u4e00\u51e11984"}, "title": {"link": "https://movie.douban.com/review/5003161/", "name": "\u6076\u9b54\u7684\u300a\u54c8\u5229\u8def\u4e9a\u300b\u624d\u662f\u5929\u7c41"}}, {"rating": "4", "author": {"link": "https://www.douban.com/people/36709953/", "name": "\u7c73\u7c92\u513f"}, "title": {"link": "https://movie.douban.com/review/4924868/", "name": "\u8f6c\u5e16\uff1a\u6559\u5802\u91cc\u7684\u67aa\u6218\uff1a\u63ed\u79d8\u5434\u5b87\u68ee\u7684\u66b4\u529b\u7f8e\u5b66(\u56fe)"}}, {"rating": "4", "author": {"link": "https://www.douban.com/people/46668263/", "name": "conan"}, "title": {"link": "https://movie.douban.com/review/4889941/", "name": "suck my tongue,peach!"}}, {"rating": "5", "author": {"link": "https://www.douban.com/people/42448701/", "name": "\u534a\u591c\u53bb\u5077\u72d7"}, "title": {"link": "https://movie.douban.com/review/4721417/", "name": "\u4e00\u90e8\u7535\u5f71\u8ba9\u6211\u559c\u6b22\u4e0a\u4e86\u4e24\u4e2a\u6f14\u5458"}}, {"rating": "5", "author": {"link": "https://www.douban.com/people/49672833/", "name": "SebastianYu"}, "title": {"link": "https://movie.douban.com/review/4701715/", "name": "\u4ec0\u4e48\u53eb\u505a\u574f\u86cb\uff1f"}}, {"rating": "5", "author": {"link": "https://www.douban.com/people/47736580/", "name": "\u79c1\u60f3\u8005"}, "title": {"link": "https://movie.douban.com/review/4531723/", "name": "Perfect"}}, {"rating": "4", "author": {"link": "https://www.douban.com/people/47886977/", "name": "\u6728\u5b50\u661f"}, "title": {"link": "https://movie.douban.com/review/4504247/", "name": "\u955c\u4e2d\u4eba,\u4eba\u975e\u5df1"}}, {"rating": "5", "author": {"link": "https://www.douban.com/people/hondaren/", "name": "Gary"}, "title": {"link": "https://movie.douban.com/review/3819563/", "name": "\u5982\u679c\u6211\u56de\u4e0d\u5230\u81ea\u5df1\u539f\u6765\u7684\u4e16\u754c..."}}, {"rating": "5", "author": {"link": "https://www.douban.com/people/45568826/", "name": "love\u9c7c"}, "title": {"link": "https://movie.douban.com/review/3693228/", "name": "\u53d8\u8138"}}, {"rating": "4", "author": {"link": "https://www.douban.com/people/2987702/", "name": "\u4eba\u8270\u4e0d\u62c6"}, "title": {"link": "https://movie.douban.com/review/3586981/", "name": "\u8c01\u662f\u8c01\u7684\u8138\u3002\u3002"}}, {"rating": "5", "author": {"link": "https://www.douban.com/people/44929910/", "name": "\u964d\u9f99\u7f57\u5bbe\u6c49"}, "title": {"link": "https://movie.douban.com/review/3561952/", "name": "\u90a3\u4e2a\u5e74\u4ee3\u7684\u521b\u65b0\u9886\u57df\u4e4b\u4f5c\u3002"}}, {"rating": "5", "author": {"link": "https://www.douban.com/people/44029750/", "name": "mollice"}, "title": {"link": "https://movie.douban.com/review/3547776/", "name": "\u4e0e\u81ea\u5df1\u7684\u6218\u6597\u2014\u2014\u300a\u53d8\u8138\u300b\u6709\u611f"}}, {"rating": "5", "author": {"link": "https://www.douban.com/people/valerie0305/", "name": "\u6211\u7231\u6211\u7684\u5c0f\u96c0\u6591"}, "title": {"link": "https://movie.douban.com/review/3359546/", "name": "\u7ecf\u5178"}}, {"rating": "5", "author": {"link": "https://www.douban.com/people/33761700/", "name": "fmdou"}, "title": {"link": "https://movie.douban.com/review/3289775/", "name": "\u6211\u88ab\u97e9\u5267\u6bd2\u5bb3\u4e86"}}, {"rating": "4", "author": {"link": "https://www.douban.com/people/34951872/", "name": "\u6c34\u6155\u5929\u6210"}, "title": {"link": "https://movie.douban.com/review/2988985/", "name": "\u629a\u6478\u7231\u4eba\u7684\u8138\uff0c\u8bb0\u5fc6\u5fe7\u6df1"}}, {"rating": "5", "author": {"link": "https://www.douban.com/people/g.wh361/", "name": "High\u5efa\u7b51\u5e08"}, "title": {"link": "https://movie.douban.com/review/2902840/", "name": "\u4e0d\u540c\u7684\u8eab\u4efd\uff0c\u4ea4\u7ec7\u7684\u60c5\u611f\u3002"}}, {"rating": "5", "author": {"link": "https://www.douban.com/people/kitling./", "name": "kitling"}, "title": {"link": "https://movie.douban.com/review/2860785/", "name": "\u8d5e"}}, {"rating": "3", "author": {"link": "https://www.douban.com/people/21545032/", "name": "\u4e00\u5149"}, "title": {"link": "https://movie.douban.com/review/2840908/", "name": "\u5fc3\u6709\u529b\u4e0d\u902e"}}, {"rating": "5", "author": {"link": "https://www.douban.com/people/cyq520/", "name": "[\u5df2\u6ce8\u9500]"}, "title": {"link": "https://movie.douban.com/review/2248321/", "name": "\u5bfc\u6f14\u592a\u504f\u7231Cage  \u4e86 \u4e0d\u8fc7\u6211\u4e5f\u662f"}}, {"rating": "5", "author": {"link": "https://www.douban.com/people/3475246/", "name": "\u571f\u8c46\u59ae"}, "title": {"link": "https://movie.douban.com/review/2237498/", "name": "\u7f42\u7c9f\u822c\u7684\u66b4\u529b\u82ac\u82b3"}}, {"rating": "4", "author": {"link": "https://www.douban.com/people/papazao/", "name": "papazao"}, "title": {"link": "https://movie.douban.com/review/2230299/", "name": "\u6545\u4e8b\u5f88\u7cbe\u5f69"}}, {"rating": "4", "author": {"link": "https://www.douban.com/people/2332016/", "name": "\u7eb3\u6728\u8428"}, "title": {"link": "https://movie.douban.com/review/2228259/", "name": "\u53d8\u4e0d\u53d8"}}, {"rating": "4", "author": {"link": "https://www.douban.com/people/2176907/", "name": "\u94f6\u674f\u8349\u576a"}, "title": {"link": "https://movie.douban.com/review/2165058/", "name": "\u8001\u5a46\u8ba4\u4e0d\u51fa\u5047\u8001\u516c\uff1f"}}, {"rating": "5", "author": {"link": "https://www.douban.com/people/Gau/", "name": "\u5c41\u5927\u2605\u661f"}, "title": {"link": "https://movie.douban.com/review/2160182/", "name": "\u96fb\u5f71\u751f\u6daf\u7684\u958b\u555f\u8005"}}, {"rating": "5", "author": {"link": "https://www.douban.com/people/3907866/", "name": "\u4e0d\u662f\u7ae5\u8bdd"}, "title": {"link": "https://movie.douban.com/review/2121605/", "name": "\u5c3c\u53e4\u62c9\u65af\u2022\u51ef\u5947"}}, {"rating": "3", "author": {"link": "https://www.douban.com/people/wubayue/", "name": "\u516b\u6708"}, "title": {"link": "https://movie.douban.com/review/2472181/", "name": "\u4e2d\u56fd\u5bfc\u6f14\u4e0e\u597d\u83b1\u9e1f"}}, {"rating": "5", "author": {"link": "https://www.douban.com/people/sharonliu11/", "name": "\u95f2\u4e91"}, "title": {"link": "https://movie.douban.com/review/2100432/", "name": "\u8fd9\u4e2a\u7535\u5f71\u91cc\u7684\u8ff7\u60d1"}}, {"rating": "5", "author": {"link": "https://www.douban.com/people/4459771/", "name": "\u6587\u6210\u4e3b"}, "title": {"link": "https://movie.douban.com/review/2096052/", "name": "\u7384"}}, {"rating": "4", "author": {"link": "https://www.douban.com/people/pionner/", "name": "pionner2009"}, "title": {"link": "https://movie.douban.com/review/2082155/", "name": "\u4e0d\u9519"}}, {"rating": "4", "author": {"link": "https://www.douban.com/people/4022696/", "name": "fivesea"}, "title": {"link": "https://movie.douban.com/review/2077768/", "name": "\u66b4\u529b\u7f8e\u5b66\u7684\u8bbd\u523a"}}, {"rating": "5", "author": {"link": "https://www.douban.com/people/EricYing/", "name": "\u9f20\u5df4\u58eb"}, "title": {"link": "https://movie.douban.com/review/2022941/", "name": "\u8138\u53d8\u672c\u6027\u672a\u53d8"}}, {"rating": "3", "author": {"link": "https://www.douban.com/people/Hell_Jack/", "name": "\u56ff\u4e8e\u5b9e\u52a1"}, "title": {"link": "https://movie.douban.com/review/2017483/", "name": "\u5c06\u5c31\u7740\u7ed9\u4e2a\u4e09\u661f"}}, {"rating": "5", "author": {"link": "https://www.douban.com/people/2855766/", "name": "\u4e03\u60a6\u4f55"}, "title": {"link": "https://movie.douban.com/review/1982000/", "name": "\u81ea\u6211\u7684\u8ba4\u77e5~~~\u75db\u82e6\u4e0e\u6323\u624e"}}, {"rating": "4", "author": {"link": "https://www.douban.com/people/3402698/", "name": "\u5deb\u5440\u5deb"}, "title": {"link": "https://movie.douban.com/review/1717787/", "name": "\u7cdf\u7cd5"}}, {"rating": "5", "author": {"link": "https://www.douban.com/people/1812215/", "name": "Daniel"}, "title": {"link": "https://movie.douban.com/review/1714546/", "name": "\u5434\u5b87\u68ee\u7684\u7ecf\u5178"}}, {"rating": "5", "author": {"link": "https://www.douban.com/people/wujiaming/", "name": "\u5c0b\u5728\u5c0f\u8def\u4e0a"}, "title": {"link": "https://movie.douban.com/review/1656273/", "name": "John woo"}}, {"rating": "4", "author": {"link": "https://www.douban.com/people/bbjjsweet/", "name": "Jin"}, "title": {"link": "https://movie.douban.com/review/1646673/", "name": "\u9019\u6a23\u4e00\u500b\u7537\u4eba"}}, {"rating": "5", "author": {"link": "https://www.douban.com/people/3485713/", "name": "Jane~\u963f\u5b9d"}, "title": {"link": "https://movie.douban.com/review/1625458/", "name": "\u597d\u770b~~"}}, {"rating": "5", "author": {"link": "https://www.douban.com/people/liliansue/", "name": "\u70e8\u591c\u672a\u592e"}, "title": {"link": "https://movie.douban.com/review/1622604/", "name": "\u53ea\u6709\u8fd9\u90e8\u624d\u771f\u6b63\u914d\u7684\u4e0a5\u661f\uff01"}}, {"rating": "5", "author": {"link": "https://www.douban.com/people/3074459/", "name": "\u8fc7\u5ba2"}, "title": {"link": "https://movie.douban.com/review/1559470/", "name": "\u593a\u9762\u53cc\u96c4"}}, {"rating": "5", "author": {"link": "https://www.douban.com/people/Bambus/", "name": "Bambus"}, "title": {"link": "https://movie.douban.com/review/1557875/", "name": "Somewhere over the Rainbow"}}, {"rating": "4", "author": {"link": "https://www.douban.com/people/2554116/", "name": "espers"}, "title": {"link": "https://movie.douban.com/review/1520092/", "name": "\u597d\u83b1\u575e\u9b45\u529b\u7537\u4eba-\u5c3c\u53e4\u62c9\u65af\u51ef\u5947"}}, {"rating": "3", "author": {"link": "https://www.douban.com/people/3018394/", "name": "\u91d1\u5c5e\u9aa8\u5934"}, "title": {"link": "https://movie.douban.com/review/1517162/", "name": "\u5f53\u5e74\u963f``"}}, {"rating": "5", "author": {"link": "https://www.douban.com/people/yangwenming/", "name": "\u6e29\u5e26\u5b63\u98ce\u5f52\u6765"}, "title": {"link": "https://movie.douban.com/review/1475522/", "name": "\u6e2f\u7247\u597d\u83b1\u575e\u5408\u4f5c\u7684\u7ecf\u5178"}}, {"rating": "5", "author": {"link": "https://www.douban.com/people/tulippy/", "name": "\u590f\u51dd\u5b89\u3002"}, "title": {"link": "https://movie.douban.com/review/1473430/", "name": "\u5fe7\u90c1\u5230\u6781\u81f4\u7684\u7537\u4eba\u3002"}}, {"rating": "5", "author": {"link": "https://www.douban.com/people/3537532/", "name": "Ms \u677e"}, "title": {"link": "https://movie.douban.com/review/1638528/", "name": "\u89c9\u5f97john travolta\u66f4\u80fd\u80dc\u4efb\u5f71\u5e1d"}}, {"rating": "4", "author": {"link": "https://www.douban.com/people/1591296/", "name": "have.fun.com"}, "title": {"link": "https://movie.douban.com/review/1463552/", "name": "\u5434\u5b87\u68ee\u5728\u597d\u83b1\u575e\u6700\u7cbe\u5f69\u7684\u4e00\u7247"}}, {"rating": "4", "author": {"link": "https://www.douban.com/people/1506430/", "name": "JC\u52a0\u83f2"}, "title": {"link": "https://movie.douban.com/review/1452464/", "name": "\u633a\u523a\u6fc0"}}, {"rating": "4", "author": {"link": "https://www.douban.com/people/1897420/", "name": "\u8ba1\u7b97\u5e78\u798f"}, "title": {"link": "https://movie.douban.com/review/1443977/", "name": "\u98ce\u8863\u53c8\u5439\u8d77"}}, {"rating": "5", "author": {"link": "https://www.douban.com/people/PetrelKing/", "name": "PetrelKing"}, "title": {"link": "https://movie.douban.com/review/1430278/", "name": "\u7edd\u5bf9\u7ecf\u5178\u7684\u5927\u7247\u554a~"}}, {"rating": "5", "author": {"link": "https://www.douban.com/people/2219781/", "name": "\u7121\u96fb\u6975"}, "title": {"link": "https://movie.douban.com/review/1389686/", "name": "\u6211\u559c\u6b22\u4ed6\u4eba\u7684\u8eab\u4f53"}}, {"rating": "5", "author": {"link": "https://www.douban.com/people/2364980/", "name": "\u4e09\u811a\u732b\u7684\u529f\u592b\u8981\u5230\u5bb6\u3002/"}, "title": {"link": "https://movie.douban.com/review/1383534/", "name": "\u6f14\u6280\u65e0\u53ef\u6311\u5254\uff01\u3002/"}}, {"rating": "5", "author": {"link": "https://www.douban.com/people/vanesa/", "name": "\u2606\u6653\u25ce\u9759\u2606"}, "title": {"link": "https://movie.douban.com/review/1376816/", "name": "\u5e78\u597d\u6362\u4e86\u8138\uff0c\u56e0\u4e3a\u4e0d\u559c\u6b22\u51ef\u5947\u6f14\u53cd\u6d3e"}}, {"rating": "4", "author": {"link": "https://www.douban.com/people/JuLeo/", "name": "\u4ed9\u8c37\u96fe\u9690"}, "title": {"link": "https://movie.douban.com/review/1367720/", "name": "I am a Troy!"}}, {"rating": "4", "author": {"link": "https://www.douban.com/people/dangchan/", "name": "\u6c88\u9759"}, "title": {"link": "https://movie.douban.com/review/1359414/", "name": "\u5c3c\u53e4\u62c9\u65af\u00b7\u51ef\u5947"}}, {"rating": "4", "author": {"link": "https://www.douban.com/people/1168370/", "name": "\u83c1\u541b"}, "title": {"link": "https://movie.douban.com/review/1347675/", "name": "\u65f6\u4ee3\u9020\u82f1\u96c4"}}, {"rating": "5", "author": {"link": "https://www.douban.com/people/1966186/", "name": "tanying"}, "title": {"link": "https://movie.douban.com/review/1331509/", "name": "\u98da\u6f14\u6280"}}, {"rating": "4", "author": {"link": "https://www.douban.com/people/yuliamelody/", "name": "\u9ea6\u5b50\u9ea6\u5b50"}, "title": {"link": "https://movie.douban.com/review/1255802/", "name": "\u7537\u4eba\u7684\u7535\u5f71"}}, {"rating": "undefined", "author": {"link": "https://www.douban.com/people/ilovecwr/", "name": "\u9cd7\u9c7c"}, "title": {"link": "https://movie.douban.com/review/1216100/", "name": "\u6211\u51ed\u4ec0\u4e48\u8ba4\u51fa\u4f60"}}, {"rating": "5", "author": {"link": "https://www.douban.com/people/1260952/", "name": "\u5543\u4e66\u866b"}, "title": {"link": "https://movie.douban.com/review/1157943/", "name": "\u6e2f\u5f0f\u597d\u83b1\u575e\u7684\u98ce\u683c"}}, {"rating": "5", "author": {"link": "https://www.douban.com/people/1146674/", "name": "\u96e8"}, "title": {"link": "https://movie.douban.com/review/1040137/", "name": "\u7537\u4eba"}}, {"rating": "3", "author": {"link": "https://www.douban.com/people/1135978/", "name": "mofilee"}, "title": {"link": "https://movie.douban.com/review/1036632/", "name": "\u770b\u8fc7\u51e0\u904d"}}, {"rating": "5", "author": {"link": "https://www.douban.com/people/1096026/", "name": "cherryx"}, "title": {"link": "https://movie.douban.com/review/1036008/", "name": "\u6b63\u4e0e\u53cd"}}, {"rating": "5", "author": {"link": "https://www.douban.com/people/1099531/", "name": "\u4e91\u5fa1\u98ce\u884c"}, "title": {"link": "https://movie.douban.com/review/1026208/", "name": "\u5f53\u4e4b\u65e0\u6127\u7684\u7ecf\u5178\u4e4b\u4f5c"}}, {"rating": "4", "author": {"link": "https://www.douban.com/people/gzh1217/", "name": "\u9e3d\u5b50\u98de"}, "title": {"link": "https://movie.douban.com/review/7862007/", "name": "\u5267\u60c5\u65e0\u4eae\u70b9\uff0c\u6f14\u5458\u5f88\u4e0d\u9519"}}, {"rating": "4", "author": {"link": "https://www.douban.com/people/135497477/", "name": "Walker ,"}, "title": {"link": "https://movie.douban.com/review/7745406/", "name": "\u6251\u8857\u4e4b\u738b\u7684\u597d\u7535\u5f71\u3002"}}, {"rating": "4", "author": {"link": "https://www.douban.com/people/62184065/", "name": "\u6c34\u661f"}, "title": {"link": "https://movie.douban.com/review/7648832/", "name": "\u4e0d\u6362\u56de\u6765\u4e5f\u597d"}}, {"rating": "4", "author": {"link": "https://www.douban.com/people/62184065/", "name": "\u6c34\u661f"}, "title": {"link": "https://movie.douban.com/review/7648831/", "name": "\u4e0d\u6362\u56de\u6765\u4e5f\u597d"}}, {"rating": "4", "author": {"link": "https://www.douban.com/people/133353519/", "name": "hwz3335"}, "title": {"link": "https://movie.douban.com/review/7576470/", "name": "\u8fd9\u662f\u4e00\u7bc7\u597d\u6587\u7ae0"}}, {"rating": "4", "author": {"link": "https://www.douban.com/people/55479330/", "name": "Mvccc"}, "title": {"link": "https://movie.douban.com/review/7560993/", "name": "\u6211\u4eec\u90fd\u662f\u6234\u7740\u9762\u5177\u7684\u4eba"}}, {"rating": "4", "author": {"link": "https://www.douban.com/people/130381349/", "name": "\u503e\u542c\u591c\u58f0"}, "title": {"link": "https://movie.douban.com/review/7512226/", "name": "\u4e00\u70b9\u5c0f\u5c0f\u7684\u611f\u53d7"}}, {"rating": "5", "author": {"link": "https://www.douban.com/people/104310668/", "name": "\u6c89\u6d6e\u7535\u5f71"}, "title": {"link": "https://movie.douban.com/review/7505561/", "name": "\u5434\u5b87\u68ee\u300a\u53d8\u8138\u300b\u2014\u2014\u5206\u955c\u5934\u5267\u672c\u6897\u6982"}}, {"rating": "5", "author": {"link": "https://www.douban.com/people/92062002/", "name": "\u84dd\u5149\u5c0f\u8d85\u4eba"}, "title": {"link": "https://movie.douban.com/review/7504689/", "name": "\u53e6\u4e00\u79cd\u5267\u4f5c\u601d\u7ef4"}}, {"rating": "3", "author": {"link": "https://www.douban.com/people/123586799/", "name": "\u6797\u5915"}, "title": {"link": "https://movie.douban.com/review/7500911/", "name": "\u6d45\u8c08\u300a\u53d8\u8138\u300b"}}, {"rating": "5", "author": {"link": "https://www.douban.com/people/125911467/", "name": "Mr\u90d1"}, "title": {"link": "https://movie.douban.com/review/7482825/", "name": "\u6027\u683c\u51b3\u5b9a\u547d\u8fd0"}}, {"rating": "5", "author": {"link": "https://www.douban.com/people/57951298/", "name": "\u7ea0\u7ed3\u7684A\u578b"}, "title": {"link": "https://movie.douban.com/review/7462460/", "name": "\u8ba4\u8bc6\u597d\u83b1\u575e"}}, {"rating": "5", "author": {"link": "https://www.douban.com/people/121549348/", "name": "Once"}, "title": {"link": "https://movie.douban.com/review/7433112/", "name": "\u4e09\u4e2a\u4eba\u7684\u5dc5\u5cf0\u4e4b\u4f5c"}}, {"rating": "4", "author": {"link": "https://www.douban.com/people/102618266/", "name": "\u5ffd\u60a0xi"}, "title": {"link": "https://movie.douban.com/review/7374976/", "name": "Face/Off"}}, {"rating": "3", "author": {"link": "https://www.douban.com/people/116290730/", "name": "\u86c7\u7cbe\u75c5\u4eba"}, "title": {"link": "https://movie.douban.com/review/7288352/", "name": "\u6ca1\u6709\u9884\u544a\u7247\u597d\u770b2333"}}, {"rating": "5", "author": {"link": "https://www.douban.com/people/103558834/", "name": "camilla"}, "title": {"link": "https://movie.douban.com/review/7155577/", "name": "\u5434\u5b87\u68ee\uff0c\u5f88\u4f69\u670d\u4f60\uff01(\u6700\u559c\u6b22\u770b\u7684\u4e00\u90e8\u7535\u5f71!\u4ee5\u4e0b\u5f71..."}}, {"rating": "4", "author": {"link": "https://www.douban.com/people/52572494/", "name": "\u98de\u8dc3\u65f6\u7a7a"}, "title": {"link": "https://movie.douban.com/review/7115630/", "name": "\u7075\u9b42\u4e0e\u8089\u4f53\u7684\u4e89\u8bba\u4e0e\u63a2\u8ba8\u66f4\u5c06\u5ef6\u7eed"}}, {"rating": "4", "author": {"link": "https://www.douban.com/people/54570246/", "name": "Deer"}, "title": {"link": "https://movie.douban.com/review/7110375/", "name": "\u4ed6\u8ba9\u4f60\u96be\u8fc7\uff0c\u53ef\u4f60\u8fd8\u7231\u4ed6"}}, {"rating": "4", "author": {"link": "https://www.douban.com/people/4036437/", "name": "Exquisiteness"}, "title": {"link": "https://movie.douban.com/review/6802227/", "name": "\u6458\u6284\uff1a\u7259\u75db\u7684\u543b"}}, {"rating": "5", "author": {"link": "https://www.douban.com/people/52417187/", "name": "\u5927\u5199\u7684Z"}, "title": {"link": "https://movie.douban.com/review/6754137/", "name": "\u51ef\u5947\u524d\u9762\u90a3\u6bb5\u8868\u6f14\u592a\u8d5e\u4e86\uff01\uff01\uff01"}}, {"rating": "5", "author": {"link": "https://www.douban.com/people/65361064/", "name": "\u5218\u65ed"}, "title": {"link": "https://movie.douban.com/review/6524816/", "name": "\u767d\u9e3d\u3001\u6559\u5802\u548c\u5b50\u5f39\u3001\u8840\u6d46\u7684\u4ea4\u878d\uff0c\u4ea6\u662f\u6b63\u4e49\u4e0e\u90aa\u6076..."}}, {"rating": "5", "author": {"link": "https://www.douban.com/people/71366482/", "name": "seven"}, "title": {"link": "https://movie.douban.com/review/6522411/", "name": "Face"}}, {"rating": "5", "author": {"link": "https://www.douban.com/people/69032472/", "name": "\u73ab\u7470\u82b1\u5f00\u5f97\u4e0d\u665a"}, "title": {"link": "https://movie.douban.com/review/6461962/", "name": "\u53d8\u8138\u8eab\u4e0d\u53d8"}}, {"rating": "3", "author": {"link": "https://www.douban.com/people/53612071/", "name": "\u6797\u6f47\u67ab"}, "title": {"link": "https://movie.douban.com/review/6310131/", "name": "\u53d8\u7684\u662f\u8138\uff0c\u53d8\u4e0d\u4e86\u7684\u662f\u4eba\u6027"}}, {"rating": "4", "author": {"link": "https://www.douban.com/people/72777877/", "name": "W\u00b7SK"}, "title": {"link": "https://movie.douban.com/review/6310025/", "name": "\u5f88\u6709\u6e2f\u7247\u7684\u611f\u89c9"}}, {"rating": "3", "author": {"link": "https://www.douban.com/people/70734148/", "name": "\u8302\u661f\u4eba"}, "title": {"link": "https://movie.douban.com/review/5878015/", "name": "\u6211\u6700\u559c\u6b22\u7684\u5341\u5927\u5916\u8bed\u7247"}}, {"rating": "4", "author": {"link": "https://www.douban.com/people/48236283/", "name": "Ron"}, "title": {"link": "https://movie.douban.com/review/5813856/", "name": "\u53d8\u8138\u7684\u7ed3\u5c40\u7559\u4e0b\u7684\u660e\u663e\u7684\u4f0f\u7b14"}}, {"rating": "5", "author": {"link": "https://www.douban.com/people/67938765/", "name": "\u593a\u547d\u5d29\u6c99"}, "title": {"link": "https://movie.douban.com/review/5755857/", "name": "\u5982\u679c\u7ed9\u4f60\u4e00\u4e2a\u6210\u4e3a\u522b\u4eba\u7684\u673a\u4f1a"}}, {"rating": "5", "author": {"link": "https://www.douban.com/people/63090782/", "name": "Mr.Sooper"}, "title": {"link": "https://movie.douban.com/review/5755553/", "name": "\u788e\u788e\u5ff5"}}, {"rating": "5", "author": {"link": "https://www.douban.com/people/34420728/", "name": "\u5728\u8def\u4e0a\u3002"}, "title": {"link": "https://movie.douban.com/review/5688066/", "name": "\u5f88\u559c\u6b22castor troy\u7684\u6027\u683c"}}, {"rating": "4", "author": {"link": "https://www.douban.com/people/o-mm/", "name": "\u746d\u4e8c\u53d4\u53d4"}, "title": {"link": "https://movie.douban.com/review/2143903/", "name": "\u7231\u4f60\u7684\u4eba\u8fd8\u662f\u7231\u4f60\u7684\u795e?"}}, {"rating": "4", "author": {"link": "https://www.douban.com/people/lvapple/", "name": "\u6c88\u7eff"}, "title": {"link": "https://movie.douban.com/review/2041330/", "name": "\u7f42\u7c9f\u822c\u7684\u66b4\u529b\u82ac\u82b3"}}, {"rating": "4", "author": {"link": "https://www.douban.com/people/sarah747/", "name": "\u6c99\u62c9\u725b\u5976"}, "title": {"link": "https://movie.douban.com/review/1569809/", "name": "\u53d1\u73b0\u5c0f\u7834\u7efd"}}, {"rating": "4", "author": {"link": "https://www.douban.com/people/crow./", "name": "crow"}, "title": {"link": "https://movie.douban.com/review/1548662/", "name": "\u6362\u6c64\u4e0d\u6362\u836f"}}, {"rating": "5", "author": {"link": "https://www.douban.com/people/bonnymml/", "name": "\u5927\u725b\u599e"}, "title": {"link": "https://movie.douban.com/review/1283493/", "name": "\u7a7f\u8d8a\u65f6\u5149\u7684\u7ecf\u5178\u91cd\u73b0"}}, {"rating": "4", "author": {"link": "https://www.douban.com/people/mSky/", "name": "Dsky"}, "title": {"link": "https://movie.douban.com/review/1280033/", "name": "Face off\u2015\u2015\u8d4e\u7f6a\u4e0e\u7537\u4eba\u7684\u8f83\u91cf"}}, {"rating": "3", "author": {"link": "https://www.douban.com/people/1196187/", "name": "\u5929\u7a7a\u7684\u884c\u8005"}, "title": {"link": "https://movie.douban.com/review/1179720/", "name": "\u5395\u6240\u91cc\u7684\u4f73\u7247"}}, {"rating": "5", "author": {"link": "https://www.douban.com/people/1483058/", "name": "\u8001\u6768"}, "title": {"link": "https://movie.douban.com/review/1138910/", "name": "\u7ea6\u7ff0\u5c48\u4f0f\u5854"}}, {"rating": "5", "author": {"link": "https://www.douban.com/people/sotana/", "name": "\u5b81\u5b81|\u91cd\u751f"}, "title": {"link": "https://movie.douban.com/review/1033546/", "name": "\u597d\u7247"}}, {"rating": "4", "author": {"link": "https://www.douban.com/people/1024996/", "name": "72\u5c0f\u65f6\u67e0\u6aac"}, "title": {"link": "https://movie.douban.com/review/1005330/", "name": "FACE TO FACE"}}, {"rating": "3", "author": {"link": "https://www.douban.com/people/kaka2sky/", "name": "Allison"}, "title": {"link": "https://movie.douban.com/review/5504355/", "name": "\u8fd9\u5e74\u5934\u4eba\u5bb6\u90fd\u5728\u770b\u753b\u76ae\uff0c\u6211\u770b\u4e2a\u53d8\u8138\u5e94\u4e2a\u666f\u3002"}}, {"rating": "4", "author": {"link": "https://www.douban.com/people/31450057/", "name": "\u4f26\u6566\u5730\u94c1"}, "title": {"link": "https://movie.douban.com/review/3161546/", "name": "\u5c3c\u53e4\u62c9\u65af\u51ef\u5947"}}], "related_info": "\n                                \u3000\u3000\u51ef\u65af\u7279\uff08\u5c3c\u53e4\u62c9\u65af\u2022\u51ef\u5947 Nicolas Cage \u9970\uff09\u662f\u4e00\u4e2a\u6050\u6016\u5206\u5b50\uff0c\u4ed6\u672c\u60f3\u6740\u6b7b\u63a2\u5458\u897f\u6069\uff08\u7ea6\u7ff0\u2022\u7279\u62c9\u6c83\u5854 John Travolta \u9970\uff09\uff0c\u5374\u8bef\u6740\u4e86\u897f\u6069\u7684\u513f\u5b50\uff0c\u897f\u6069\u66f4\u4e0e\u51ef\u65af\u7279\u7ed3\u4e0b\u4e0d\u5171\u6234\u5929\u4e4b\u4ec7\u3002\u5728\u902e\u6355\u51ef\u65af\u7279\u5f52\u6848\u4e4b\u540e\uff0c\u4ed6\u4ee5\u4e3a\u53ef\u4ee5\u5212\u4e0a\u53e5\u53f7\uff0c\u5374\u5f97\u77e5\u51ef\u65af\u7279\u5df2\u7ecf\u628a\u4e00\u679a\u6bd2\u6c14\u70b8\u5f39\u6295\u653e\u5728\u67d0\u4e2a\u4eba\u7fa4\u5bc6\u96c6\u7684\u89d2\u843d\u3002\n                                    \n                                \u3000\u3000\u4e3a\u4e86\u67e5\u51fa\u70b8\u5f39\u5730\u70b9\uff0c\u897f\u6069\u51b3\u5b9a\u5229\u7528\u6574\u5f62\u624b\u672f\uff0c\u5c06\u660f\u8ff7\u4e2d\u7684\u51ef\u65af\u7279\u7684\u8138\u6362\u5728\u81ea\u5df1\u8eab\u4e0a\uff0c\u53bb\u5047\u626e\u51ef\u65af\u7279\u8eab\u4efd\u5957\u51fa\u4ed6\u5f1f\u5f1f\u8bf4\u51fa\u771f\u76f8\u3002\u8fd9\u4ef6\u4e8b\u5c5e\u4e8eFBI\u9ad8\u5ea6\u673a\u5bc6\uff0c\u53ea\u6709\u5be5\u5be5\u51e0\u4eba\u77e5\u60c5\u3002\n                                    \n                                \u3000\u3000\u51ef\u65af\u7279\u9192\u6765\uff0c\u6b64\u65f6\u4ed6\u6709\u7740\u897f\u6069\u7684\u9762\u76f8\u3002\u4e8e\u662f\u4ed6\u51b3\u5b9a\u5c06\u8ba1\u5c31\u8ba1\uff0c\u5c06\u77e5\u60c5\u4eba\u6740\u6389\u4e4b\u540e\uff0c\u4ed6\u5c31\u53d8\u6210\u4e86\u897f\u6069\u2026\u2026\n                        ", "award": ["\n\u7b2c70\u5c4a\u5965\u65af\u5361\u91d1\u50cf\u5956\n \u6700\u4f73\u97f3\u6548\u526a\u8f91(\u63d0\u540d) Per Hallberg\u00a0/\u00a0\u9a6c\u514b\u00b7P\u00b7\u65bd\u7279\u91d1\u683c\u5c14"], "related_movie": [{"url": "https://movie.douban.com/subject/1292728/", "name": "\n\u52c7\u95ef\u593a\u547d\u5c9b\n"}, {"url": "https://movie.douban.com/subject/1300618/", "name": "\n\u7a7a\u4e2d\u76d1\u72f1\n"}, {"url": "https://movie.douban.com/subject/1292553/", "name": "\n\u771f\u5b9e\u7684\u8c0e\u8a00\n"}, {"url": "https://movie.douban.com/subject/1308848/", "name": "\n\u56fd\u5bb6\u5b9d\u85cf\n"}, {"url": "https://movie.douban.com/subject/1293167/", "name": "\n\u751f\u6b7b\u65f6\u901f\n"}, {"url": "https://movie.douban.com/subject/1578507/", "name": "\n\u8c0d\u5f71\u91cd\u91cd3\n"}, {"url": "https://movie.douban.com/subject/1292484/", "name": "\n\u789f\u4e2d\u8c0d\n"}, {"url": "https://movie.douban.com/subject/2124586/", "name": "\n\u98d3\u98ce\u8425\u6551\n"}, {"url": "https://movie.douban.com/subject/1291844/", "name": "\n\u7ec8\u7ed3\u80052\uff1a\u5ba1\u5224\u65e5\n"}, {"url": "https://movie.douban.com/subject/1291843/", "name": "\n\u9ed1\u5ba2\u5e1d\u56fd\n"}], "interest": {"rate": "8.4", "rating_people_num": "186609", "rating_per": ["35.7%", "48.0%", "15.4%", "0.8%", "0.1%"], "rating_better": ["96% \u52a8\u4f5c\u7247", "94% \u79d1\u5e7b\u7247"]}, "year": "(1997)", "movie_url": "https://movie.douban.com/subject/1292659/"}